{"title":"Combined feed","url":"https://KPOPCORD.github.io/news/all.xml","elements":[{"title":"있지(ITZY) \"일본 정식 데뷔\"   온라인 쇼케이스 (KBS연예 ─ 음악)","contents":"<a href=\"https://kstar.kbs.co.kr/list_view.html?idx=181127\">\t<span class=\"img-box hh\">\n\t\t<span class=\"img-thum\">\n\t\t\t<span class=\"img-center\">\n\t\t\t\t<img src=\"https://entertainimg.kbsmedia.co.kr/cms/uploads/CONTENTS_20211220141952_567f2d8a2901454a0aa3a93033ccb716.jpg\" alt=\"대체 텍스트\">\n\t\t\t</span>\n\t\t</span>\n\t</span></a>\n\t<span class=\"txt\">\n\t\t<span class=\"max-progtit\"><a href=\"https://kstar.kbs.co.kr/list_view.html?idx=181127\">있지(ITZY) \"일본 정식 데뷔\"   온라인 쇼케이스 </a></span>\n\t</span>","link":"https://kstar.kbs.co.kr/list_view.html?idx=181127","retrieved":1639977645993,"image":"https://entertainimg.kbsmedia.co.kr/cms/uploads/CONTENTS_20211220141952_567f2d8a2901454a0aa3a93033ccb716.jpg"},{"title":"2021년 세계인이 가장 사랑한 K-POP 가수 '방탄소년단' (KBS연예 ─ 음악)","contents":"<a href=\"https://kstar.kbs.co.kr/list_view.html?idx=181082\">\t<span class=\"img-box hh\">\n\t\t<span class=\"img-thum\">\n\t\t\t<span class=\"img-center\">\n\t\t\t\t<img src=\"https://entertainimg.kbsmedia.co.kr/cms/uploads/CONTENTS_20211220101624_72785a826b37fc9944fab17c843ac9bd.jpg\" alt=\"대체 텍스트\">\n\t\t\t</span>\n\t\t</span>\n\t</span></a>\n\t<span class=\"txt\">\n\t\t<span class=\"max-progtit\"><a href=\"https://kstar.kbs.co.kr/list_view.html?idx=181082\">2021년 세계인이 가장 사랑한 K-POP 가수 '방탄소년단'</a></span>\n\t</span>","link":"https://kstar.kbs.co.kr/list_view.html?idx=181082","retrieved":1639967940659,"image":"https://entertainimg.kbsmedia.co.kr/cms/uploads/CONTENTS_20211220101624_72785a826b37fc9944fab17c843ac9bd.jpg"},{"title":"트와이스 월드투어, 7회 공연 전석 매진! (KBS연예 ─ 음악)","contents":"<a href=\"https://kstar.kbs.co.kr/list_view.html?idx=181057\">\t<span class=\"img-box hh\">\n\t\t<span class=\"img-thum\">\n\t\t\t<span class=\"img-center\">\n\t\t\t\t<img src=\"https://entertainimg.kbsmedia.co.kr/cms/uploads/CONTENTS_20211220100907_78309949901f7b04de31c6c3fae4ac76.jpg\" alt=\"대체 텍스트\">\n\t\t\t</span>\n\t\t</span>\n\t</span></a>\n\t<span class=\"txt\">\n\t\t<span class=\"max-progtit\"><a href=\"https://kstar.kbs.co.kr/list_view.html?idx=181057\">트와이스 월드투어, 7회 공연 전석 매진!</a></span>\n\t</span>","link":"https://kstar.kbs.co.kr/list_view.html?idx=181057","retrieved":1639967940660,"image":"https://entertainimg.kbsmedia.co.kr/cms/uploads/CONTENTS_20211220100907_78309949901f7b04de31c6c3fae4ac76.jpg"},{"title":"[콘서트] 전석 매진 포레스텔라, 장충체육관 가득 채운 압도적인 가창력! (KBS연예 ─ 음악)","contents":"<a href=\"https://kstar.kbs.co.kr/list_view.html?idx=181042\">\t<span class=\"img-box hh\">\n\t\t<span class=\"img-thum\">\n\t\t\t<span class=\"img-center\">\n\t\t\t\t<img src=\"https://entertainimg.kbsmedia.co.kr/cms/uploads/CONTENTS_20211220095638_6de7d1aca46153430571154b75445d63.jpg\" alt=\"대체 텍스트\">\n\t\t\t</span>\n\t\t</span>\n\t</span></a>\n\t<span class=\"txt\">\n\t\t<span class=\"max-progtit\"><a href=\"https://kstar.kbs.co.kr/list_view.html?idx=181042\">[콘서트] 전석 매진 포레스텔라, 장충체육관 가득 채운 압도적인 가창력!</a></span>\n\t</span>","link":"https://kstar.kbs.co.kr/list_view.html?idx=181042","retrieved":1639962541529,"image":"https://entertainimg.kbsmedia.co.kr/cms/uploads/CONTENTS_20211220095638_6de7d1aca46153430571154b75445d63.jpg"},{"title":"김준수가 전하는 '옷소매 붉은 끝동'의 감동, OST 발매 (KBS연예 ─ 음악)","contents":"<a href=\"https://kstar.kbs.co.kr/list_view.html?idx=181018\">\t<span class=\"img-box hh\">\n\t\t<span class=\"img-thum\">\n\t\t\t<span class=\"img-center\">\n\t\t\t\t<img src=\"https://entertainimg.kbsmedia.co.kr/cms/uploads/CONTENTS_20211220094511_fb07b2053a523d53d537af8524e40bf6.jpg\" alt=\"대체 텍스트\">\n\t\t\t</span>\n\t\t</span>\n\t</span></a>\n\t<span class=\"txt\">\n\t\t<span class=\"max-progtit\"><a href=\"https://kstar.kbs.co.kr/list_view.html?idx=181018\">김준수가 전하는 '옷소매 붉은 끝동'의 감동, OST 발매</a></span>\n\t</span>","link":"https://kstar.kbs.co.kr/list_view.html?idx=181018","retrieved":1639962541539,"image":"https://entertainimg.kbsmedia.co.kr/cms/uploads/CONTENTS_20211220094511_fb07b2053a523d53d537af8524e40bf6.jpg"},{"title":"빌보드가 주목한 원어스, '올해의 베스트 K-POP' (KBS연예 ─ 음악)","contents":"<a href=\"https://kstar.kbs.co.kr/list_view.html?idx=180981\">\t<span class=\"img-box hh\">\n\t\t<span class=\"img-thum\">\n\t\t\t<span class=\"img-center\">\n\t\t\t\t<img src=\"https://entertainimg.kbsmedia.co.kr/cms/uploads/CONTENTS_20211220085426_dad75c6eb88d4dd04455db2d2ba06281.jpg\" alt=\"대체 텍스트\">\n\t\t\t</span>\n\t\t</span>\n\t</span></a>\n\t<span class=\"txt\">\n\t\t<span class=\"max-progtit\"><a href=\"https://kstar.kbs.co.kr/list_view.html?idx=180981\">빌보드가 주목한 원어스, '올해의 베스트 K-POP' </a></span>\n\t</span>","link":"https://kstar.kbs.co.kr/list_view.html?idx=180981","retrieved":1639962541542,"image":"https://entertainimg.kbsmedia.co.kr/cms/uploads/CONTENTS_20211220085426_dad75c6eb88d4dd04455db2d2ba06281.jpg"},{"title":"방탄소년단, 美 제임스 코든 쇼 출연 (KBS연예 ─ 음악)","contents":"<a href=\"https://kstar.kbs.co.kr/list_view.html?idx=180497\">\t<span class=\"img-box hh\">\n\t\t<span class=\"img-thum\">\n\t\t\t<span class=\"img-center\">\n\t\t\t\t<img src=\"https://entertainimg.kbsmedia.co.kr/cms/uploads/CONTENTS_20211217172406_6dc6e155f9db68aa2b9bcefaaed54b97.jpg\" alt=\"대체 텍스트\">\n\t\t\t</span>\n\t\t</span>\n\t</span></a>\n\t<span class=\"txt\">\n\t\t<span class=\"max-progtit\"><a href=\"https://kstar.kbs.co.kr/list_view.html?idx=180497\">방탄소년단, 美 제임스 코든 쇼 출연 </a></span>\n\t</span>","link":"https://kstar.kbs.co.kr/list_view.html?idx=180497","retrieved":1639729504921,"image":"https://entertainimg.kbsmedia.co.kr/cms/uploads/CONTENTS_20211217172406_6dc6e155f9db68aa2b9bcefaaed54b97.jpg"},{"title":"이루마 데뷔 20주년, 조수미 참여한 '쿠오레 인디고' 발매 (KBS연예 ─ 음악)","contents":"<a href=\"https://kstar.kbs.co.kr/list_view.html?idx=180340\">\t<span class=\"img-box hh\">\n\t\t<span class=\"img-thum\">\n\t\t\t<span class=\"img-center\">\n\t\t\t\t<img src=\"https://entertainimg.kbsmedia.co.kr/cms/uploads/CONTENTS_20211217094450_4317bfd8dc9265a002ea8f2ea4fd3f61.jpg\" alt=\"대체 텍스트\">\n\t\t\t</span>\n\t\t</span>\n\t</span></a>\n\t<span class=\"txt\">\n\t\t<span class=\"max-progtit\"><a href=\"https://kstar.kbs.co.kr/list_view.html?idx=180340\">이루마 데뷔 20주년, 조수미 참여한 '쿠오레 인디고' 발매</a></span>\n\t</span>","link":"https://kstar.kbs.co.kr/list_view.html?idx=180340","retrieved":1639703341946,"image":"https://entertainimg.kbsmedia.co.kr/cms/uploads/CONTENTS_20211217094450_4317bfd8dc9265a002ea8f2ea4fd3f61.jpg"},{"title":"세븐틴 리더 에스쿱스 \"진심으로 감사하게 생각\" (KBS연예 ─ 음악)","contents":"<a href=\"https://kstar.kbs.co.kr/list_view.html?idx=180187\">\t<span class=\"img-box hh\">\n\t\t<span class=\"img-thum\">\n\t\t\t<span class=\"img-center\">\n\t\t\t\t<img src=\"https://entertainimg.kbsmedia.co.kr/cms/uploads/CONTENTS_20211216135055_2893d71818ae7c2900f4e38e9cf6a86b.jpg\" alt=\"대체 텍스트\">\n\t\t\t</span>\n\t\t</span>\n\t</span></a>\n\t<span class=\"txt\">\n\t\t<span class=\"max-progtit\"><a href=\"https://kstar.kbs.co.kr/list_view.html?idx=180187\">세븐틴 리더 에스쿱스 \"진심으로 감사하게 생각\"</a></span>\n\t</span>","link":"https://kstar.kbs.co.kr/list_view.html?idx=180187","retrieved":1639631960395,"image":"https://entertainimg.kbsmedia.co.kr/cms/uploads/CONTENTS_20211216135055_2893d71818ae7c2900f4e38e9cf6a86b.jpg"},{"title":"겨울 감성 발라더 정승환, '별'로 다시 차트 정상 노린다 (KBS연예 ─ 음악)","contents":"<a href=\"https://kstar.kbs.co.kr/list_view.html?idx=180131\">\t<span class=\"img-box hh\">\n\t\t<span class=\"img-thum\">\n\t\t\t<span class=\"img-center\">\n\t\t\t\t<img src=\"https://entertainimg.kbsmedia.co.kr/cms/uploads/CONTENTS_20211216092513_9bca1042c5c4c77c28aade9bc85060cb.jpg\" alt=\"대체 텍스트\">\n\t\t\t</span>\n\t\t</span>\n\t</span></a>\n\t<span class=\"txt\">\n\t\t<span class=\"max-progtit\"><a href=\"https://kstar.kbs.co.kr/list_view.html?idx=180131\">겨울 감성 발라더 정승환, '별'로 다시 차트 정상 노린다</a></span>\n\t</span>","link":"https://kstar.kbs.co.kr/list_view.html?idx=180131","retrieved":1639628828649,"image":"https://entertainimg.kbsmedia.co.kr/cms/uploads/CONTENTS_20211216092513_9bca1042c5c4c77c28aade9bc85060cb.jpg"},{"title":"[뮤비가 좋다] 10년 공백 무색하게 만든 하하의 컴백 '공백' (KBS연예 ─ 음악)","contents":"<a href=\"https://kstar.kbs.co.kr/list_view.html?idx=180010\">\t<span class=\"img-box hh\">\n\t\t<span class=\"img-thum\">\n\t\t\t<span class=\"img-center\">\n\t\t\t\t<img src=\"https://entertainimg.kbsmedia.co.kr/cms/uploads/CONTENTS_20211215103522_e035b10f2e1f116be1231e01bca80d15.jpg\" alt=\"대체 텍스트\">\n\t\t\t</span>\n\t\t</span>\n\t</span></a>\n\t<span class=\"txt\">\n\t\t<span class=\"max-progtit\"><a href=\"https://kstar.kbs.co.kr/list_view.html?idx=180010\">[뮤비가 좋다] 10년 공백 무색하게 만든 하하의 컴백 '공백'</a></span>\n\t</span>","link":"https://kstar.kbs.co.kr/list_view.html?idx=180010","retrieved":1639535742211,"image":"https://entertainimg.kbsmedia.co.kr/cms/uploads/CONTENTS_20211215103522_e035b10f2e1f116be1231e01bca80d15.jpg"},{"title":"트와이스, 월드투어 초고속 매진에 추가 개최 결정! (KBS연예 ─ 음악)","contents":"<a href=\"https://kstar.kbs.co.kr/list_view.html?idx=179856\">\t<span class=\"img-box hh\">\n\t\t<span class=\"img-thum\">\n\t\t\t<span class=\"img-center\">\n\t\t\t\t<img src=\"https://entertainimg.kbsmedia.co.kr/cms/uploads/CONTENTS_20211214162838_41c2b854106d84390bf8c582ec5aeebc.jpg\" alt=\"대체 텍스트\">\n\t\t\t</span>\n\t\t</span>\n\t</span></a>\n\t<span class=\"txt\">\n\t\t<span class=\"max-progtit\"><a href=\"https://kstar.kbs.co.kr/list_view.html?idx=179856\">트와이스, 월드투어 초고속 매진에 추가 개최 결정!</a></span>\n\t</span>","link":"https://kstar.kbs.co.kr/list_view.html?idx=179856","retrieved":1639470317886,"image":"https://entertainimg.kbsmedia.co.kr/cms/uploads/CONTENTS_20211214162838_41c2b854106d84390bf8c582ec5aeebc.jpg"},{"title":"[콘서트] 입대 앞둔 온앤오프 \"행복한 순간들에는 항상 퓨즈가 있었다\" (KBS연예 ─ 음악)","contents":"<a href=\"https://kstar.kbs.co.kr/list_view.html?idx=179833\">\t<span class=\"img-box hh\">\n\t\t<span class=\"img-thum\">\n\t\t\t<span class=\"img-center\">\n\t\t\t\t<img src=\"https://entertainimg.kbsmedia.co.kr/cms/uploads/CONTENTS_20211214153956_21996c7be7e62881ed0b9cd705099c90.jpg\" alt=\"대체 텍스트\">\n\t\t\t</span>\n\t\t</span>\n\t</span></a>\n\t<span class=\"txt\">\n\t\t<span class=\"max-progtit\"><a href=\"https://kstar.kbs.co.kr/list_view.html?idx=179833\">[콘서트] 입대 앞둔 온앤오프 \"행복한 순간들에는 항상 퓨즈가 있었다\"</a></span>\n\t</span>","link":"https://kstar.kbs.co.kr/list_view.html?idx=179833","retrieved":1639466398412,"image":"https://entertainimg.kbsmedia.co.kr/cms/uploads/CONTENTS_20211214153956_21996c7be7e62881ed0b9cd705099c90.jpg"},{"title":"김재환 전곡 프로듀싱 컴백  \"다 잊은 줄 알았어\" (KBS연예 ─ 음악)","contents":"<a href=\"https://kstar.kbs.co.kr/list_view.html?idx=179785\">\t<span class=\"img-box hh\">\n\t\t<span class=\"img-thum\">\n\t\t\t<span class=\"img-center\">\n\t\t\t\t<img src=\"https://entertainimg.kbsmedia.co.kr/cms/uploads/CONTENTS_20211214094131_4720d2062dc4bbc668925842d653e922.jpg\" alt=\"대체 텍스트\">\n\t\t\t</span>\n\t\t</span>\n\t</span></a>\n\t<span class=\"txt\">\n\t\t<span class=\"max-progtit\"><a href=\"https://kstar.kbs.co.kr/list_view.html?idx=179785\">김재환 전곡 프로듀싱 컴백  \"다 잊은 줄 알았어\" </a></span>\n\t</span>","link":"https://kstar.kbs.co.kr/list_view.html?idx=179785","retrieved":1639444195913,"image":"https://entertainimg.kbsmedia.co.kr/cms/uploads/CONTENTS_20211214094131_4720d2062dc4bbc668925842d653e922.jpg"},{"title":"크리스마스 캐롤 ‘조선판스타’ 국악싱글 앨범 (KBS연예 ─ 음악)","contents":"<a href=\"https://kstar.kbs.co.kr/list_view.html?idx=179528\">\t<span class=\"img-box hh\">\n\t\t<span class=\"img-thum\">\n\t\t\t<span class=\"img-center\">\n\t\t\t\t<img src=\"https://entertainimg.kbsmedia.co.kr/cms/uploads/CONTENTS_20211213112414_db32bc35b293937a7fb044f23c96db0f.jpg\" alt=\"대체 텍스트\">\n\t\t\t</span>\n\t\t</span>\n\t</span></a>\n\t<span class=\"txt\">\n\t\t<span class=\"max-progtit\"><a href=\"https://kstar.kbs.co.kr/list_view.html?idx=179528\">크리스마스 캐롤 ‘조선판스타’ 국악싱글 앨범  </a></span>\n\t</span>","link":"https://kstar.kbs.co.kr/list_view.html?idx=179528","retrieved":1639363027068,"image":"https://entertainimg.kbsmedia.co.kr/cms/uploads/CONTENTS_20211213112414_db32bc35b293937a7fb044f23c96db0f.jpg"},{"title":"마마무 문별과 래퍼 미란이의 환상 케미스트리! 'G999' 발매! (KBS연예 ─ 음악)","contents":"<a href=\"https://kstar.kbs.co.kr/list_view.html?idx=179503\">\t<span class=\"img-box hh\">\n\t\t<span class=\"img-thum\">\n\t\t\t<span class=\"img-center\">\n\t\t\t\t<img src=\"https://entertainimg.kbsmedia.co.kr/cms/uploads/CONTENTS_20211213101237_d3ca441377a5ac27b417500b14ad4e7c.jpg\" alt=\"대체 텍스트\">\n\t\t\t</span>\n\t\t</span>\n\t</span></a>\n\t<span class=\"txt\">\n\t\t<span class=\"max-progtit\"><a href=\"https://kstar.kbs.co.kr/list_view.html?idx=179503\">마마무 문별과 래퍼 미란이의 환상 케미스트리! 'G999' 발매!</a></span>\n\t</span>","link":"https://kstar.kbs.co.kr/list_view.html?idx=179503","retrieved":1639363027068,"image":"https://entertainimg.kbsmedia.co.kr/cms/uploads/CONTENTS_20211213101237_d3ca441377a5ac27b417500b14ad4e7c.jpg"},{"title":"[콘서트] 우즈 단독 콘서트, 매력으로 꽉 채운 120분 (KBS연예 ─ 음악)","contents":"<a href=\"https://kstar.kbs.co.kr/list_view.html?idx=179482\">\t<span class=\"img-box ww\">\n\t\t<span class=\"img-thum\">\n\t\t\t<span class=\"img-center\">\n\t\t\t\t<img src=\"https://entertainimg.kbsmedia.co.kr/cms/uploads/CONTENTS_20211213095820_cb7fd8c0b125615649be470b7d9a49c2.jpg\" alt=\"대체 텍스트\">\n\t\t\t</span>\n\t\t</span>\n\t</span></a>\n\t<span class=\"txt\">\n\t\t<span class=\"max-progtit\"><a href=\"https://kstar.kbs.co.kr/list_view.html?idx=179482\">[콘서트] 우즈 단독 콘서트, 매력으로 꽉 채운 120분</a></span>\n\t</span>","link":"https://kstar.kbs.co.kr/list_view.html?idx=179482","retrieved":1639363027068,"image":"https://entertainimg.kbsmedia.co.kr/cms/uploads/CONTENTS_20211213095820_cb7fd8c0b125615649be470b7d9a49c2.jpg"},{"title":"백아연, '온에어' 통해 팬들과 소통! (KBS연예 ─ 음악)","contents":"<a href=\"https://kstar.kbs.co.kr/list_view.html?idx=179449\">\t<span class=\"img-box hh\">\n\t\t<span class=\"img-thum\">\n\t\t\t<span class=\"img-center\">\n\t\t\t\t<img src=\"https://entertainimg.kbsmedia.co.kr/cms/uploads/CONTENTS_20211213093816_d1caefe65256d8ac3b8c5cc3277088b9.jpg\" alt=\"대체 텍스트\">\n\t\t\t</span>\n\t\t</span>\n\t</span></a>\n\t<span class=\"txt\">\n\t\t<span class=\"max-progtit\"><a href=\"https://kstar.kbs.co.kr/list_view.html?idx=179449\">백아연, '온에어' 통해 팬들과 소통!</a></span>\n\t</span>","link":"https://kstar.kbs.co.kr/list_view.html?idx=179449","retrieved":1639363027068,"image":"https://entertainimg.kbsmedia.co.kr/cms/uploads/CONTENTS_20211213093816_d1caefe65256d8ac3b8c5cc3277088b9.jpg"},{"title":"온앤오프, 뜨거운 컴백 열기! (KBS연예 ─ 음악)","contents":"<a href=\"https://kstar.kbs.co.kr/list_view.html?idx=178821\">\t<span class=\"img-box hh\">\n\t\t<span class=\"img-thum\">\n\t\t\t<span class=\"img-center\">\n\t\t\t\t<img src=\"https://entertainimg.kbsmedia.co.kr/cms/uploads/CONTENTS_20211210154638_efe613b5c6fa2dce5daac68635a60e96.jpg\" alt=\"대체 텍스트\">\n\t\t\t</span>\n\t\t</span>\n\t</span></a>\n\t<span class=\"txt\">\n\t\t<span class=\"max-progtit\"><a href=\"https://kstar.kbs.co.kr/list_view.html?idx=178821\">온앤오프, 뜨거운 컴백 열기!</a></span>\n\t</span>","link":"https://kstar.kbs.co.kr/list_view.html?idx=178821","retrieved":1639120795917,"image":"https://entertainimg.kbsmedia.co.kr/cms/uploads/CONTENTS_20211210154638_efe613b5c6fa2dce5daac68635a60e96.jpg"},{"title":"세븐틴 '아이노치카라' 오리콘 차트 정상 오르다 (KBS연예 ─ 음악)","contents":"<a href=\"https://kstar.kbs.co.kr/list_view.html?idx=178800\">\t<span class=\"img-box hh\">\n\t\t<span class=\"img-thum\">\n\t\t\t<span class=\"img-center\">\n\t\t\t\t<img src=\"https://entertainimg.kbsmedia.co.kr/cms/uploads/CONTENTS_20211210153651_9b8228fdcc636df165247a1868491cd2.jpg\" alt=\"대체 텍스트\">\n\t\t\t</span>\n\t\t</span>\n\t</span></a>\n\t<span class=\"txt\">\n\t\t<span class=\"max-progtit\"><a href=\"https://kstar.kbs.co.kr/list_view.html?idx=178800\">세븐틴 '아이노치카라' 오리콘 차트 정상 오르다</a></span>\n\t</span>","link":"https://kstar.kbs.co.kr/list_view.html?idx=178800","retrieved":1639120795919,"image":"https://entertainimg.kbsmedia.co.kr/cms/uploads/CONTENTS_20211210153651_9b8228fdcc636df165247a1868491cd2.jpg"},{"title":"[화보] 임윤아, 매거진 '얼루어' 커버 (KBS연예 ─ 연예)","contents":"<a href=\"https://kstar.kbs.co.kr/list_view.html?idx=181220\">\t<span class=\"img-box hh\">\n\t\t<span class=\"img-thum\">\n\t\t\t<span class=\"img-center\">\n\t\t\t\t<img src=\"https://entertainimg.kbsmedia.co.kr/cms/uploads/CONTENTS_20211220165148_29c608aeb1dfab2cce63846af6411919.jpg\" alt=\"대체 텍스트\">\n\t\t\t</span>\n\t\t</span>\n\t</span></a>\n\t<span class=\"txt\">\n\t\t<span class=\"max-progtit\"><a href=\"https://kstar.kbs.co.kr/list_view.html?idx=181220\">[화보] 임윤아, 매거진 '얼루어' 커버 </a></span>\n\t</span>","link":"https://kstar.kbs.co.kr/list_view.html?idx=181220","retrieved":1639995825236,"image":"https://entertainimg.kbsmedia.co.kr/cms/uploads/CONTENTS_20211220165148_29c608aeb1dfab2cce63846af6411919.jpg"},{"title":"\"빅토리아 시대 책 읽는 여자\" 레드북, 한국뮤지컬어워즈 7개 부문 노미네이트 (KBS연예 ─ 연예)","contents":"<a href=\"https://kstar.kbs.co.kr/list_view.html?idx=181209\">\t<span class=\"img-box hh\">\n\t\t<span class=\"img-thum\">\n\t\t\t<span class=\"img-center\">\n\t\t\t\t<img src=\"https://entertainimg.kbsmedia.co.kr/cms/uploads/CONTENTS_20211220162534_8396603f121a6eb4e76bff2e9d229637.jpg\" alt=\"대체 텍스트\">\n\t\t\t</span>\n\t\t</span>\n\t</span></a>\n\t<span class=\"txt\">\n\t\t<span class=\"max-progtit\"><a href=\"https://kstar.kbs.co.kr/list_view.html?idx=181209\">\"빅토리아 시대 책 읽는 여자\" 레드북, 한국뮤지컬어워즈 7개 부문 노미네이트</a></span>\n\t</span>","link":"https://kstar.kbs.co.kr/list_view.html?idx=181209","retrieved":1639995825237,"image":"https://entertainimg.kbsmedia.co.kr/cms/uploads/CONTENTS_20211220162534_8396603f121a6eb4e76bff2e9d229637.jpg"},{"title":"\"당신의 원픽 아티스트는 누구?\" 골든디스크 인기상 투표 시작! (KBS연예 ─ 연예)","contents":"<a href=\"https://kstar.kbs.co.kr/list_view.html?idx=181034\">\t<span class=\"img-box hh\">\n\t\t<span class=\"img-thum\">\n\t\t\t<span class=\"img-center\">\n\t\t\t\t<img src=\"https://entertainimg.kbsmedia.co.kr/cms/uploads/CONTENTS_20211220095140_269472fb59cc8345efeb71a508fda5c0.jpg\" alt=\"대체 텍스트\">\n\t\t\t</span>\n\t\t</span>\n\t</span></a>\n\t<span class=\"txt\">\n\t\t<span class=\"max-progtit\"><a href=\"https://kstar.kbs.co.kr/list_view.html?idx=181034\">\"당신의 원픽 아티스트는 누구?\" 골든디스크 인기상 투표 시작!</a></span>\n\t</span>","link":"https://kstar.kbs.co.kr/list_view.html?idx=181034","retrieved":1639974503576,"image":"https://entertainimg.kbsmedia.co.kr/cms/uploads/CONTENTS_20211220095140_269472fb59cc8345efeb71a508fda5c0.jpg"},{"title":"SF9 유태양의 뮤지컬 배우 신고식! (KBS연예 ─ 연예)","contents":"<a href=\"https://kstar.kbs.co.kr/list_view.html?idx=181029\">\t<span class=\"img-box hh\">\n\t\t<span class=\"img-thum\">\n\t\t\t<span class=\"img-center\">\n\t\t\t\t<img src=\"https://entertainimg.kbsmedia.co.kr/cms/uploads/CONTENTS_20211220095005_813f04c9131d086791086c991a5dc776.jpg\" alt=\"대체 텍스트\">\n\t\t\t</span>\n\t\t</span>\n\t</span></a>\n\t<span class=\"txt\">\n\t\t<span class=\"max-progtit\"><a href=\"https://kstar.kbs.co.kr/list_view.html?idx=181029\">SF9 유태양의 뮤지컬 배우 신고식!</a></span>\n\t</span>","link":"https://kstar.kbs.co.kr/list_view.html?idx=181029","retrieved":1639974503580,"image":"https://entertainimg.kbsmedia.co.kr/cms/uploads/CONTENTS_20211220095005_813f04c9131d086791086c991a5dc776.jpg"},{"title":"포레스텔라 고우림, 솔로 활동 계약 체결! (KBS연예 ─ 연예)","contents":"<a href=\"https://kstar.kbs.co.kr/list_view.html?idx=181013\">\t<span class=\"img-box hh\">\n\t\t<span class=\"img-thum\">\n\t\t\t<span class=\"img-center\">\n\t\t\t\t<img src=\"https://entertainimg.kbsmedia.co.kr/cms/uploads/CONTENTS_20211220094033_7c248f5422e76fd0c79b5a886cf406ba.jpg\" alt=\"대체 텍스트\">\n\t\t\t</span>\n\t\t</span>\n\t</span></a>\n\t<span class=\"txt\">\n\t\t<span class=\"max-progtit\"><a href=\"https://kstar.kbs.co.kr/list_view.html?idx=181013\">포레스텔라 고우림, 솔로 활동 계약 체결!</a></span>\n\t</span>","link":"https://kstar.kbs.co.kr/list_view.html?idx=181013","retrieved":1639974503580,"image":"https://entertainimg.kbsmedia.co.kr/cms/uploads/CONTENTS_20211220094033_7c248f5422e76fd0c79b5a886cf406ba.jpg"},{"title":"윌라 오디오북, 베르나르 베르베르 신작 '문명' 출시 (KBS연예 ─ 연예)","contents":"<a href=\"https://kstar.kbs.co.kr/list_view.html?idx=180996\">\t<span class=\"img-box hh\">\n\t\t<span class=\"img-thum\">\n\t\t\t<span class=\"img-center\">\n\t\t\t\t<img src=\"https://entertainimg.kbsmedia.co.kr/cms/uploads/CONTENTS_20211220090045_9daf09a191ed94095857d82cb203db6c_1.jpg\" alt=\"대체 텍스트\">\n\t\t\t</span>\n\t\t</span>\n\t</span></a>\n\t<span class=\"txt\">\n\t\t<span class=\"max-progtit\"><a href=\"https://kstar.kbs.co.kr/list_view.html?idx=180996\">윌라 오디오북, 베르나르 베르베르 신작 '문명' 출시</a></span>\n\t</span>","link":"https://kstar.kbs.co.kr/list_view.html?idx=180996","retrieved":1639974503582,"image":"https://entertainimg.kbsmedia.co.kr/cms/uploads/CONTENTS_20211220090045_9daf09a191ed94095857d82cb203db6c_1.jpg"},{"title":"[SBS연예대상]  차은우 \"오늘은 SBS에서 하트~\" (KBS연예 ─ 연예)","contents":"<a href=\"https://kstar.kbs.co.kr/list_view.html?idx=180815\">\t<span class=\"img-box hh\">\n\t\t<span class=\"img-thum\">\n\t\t\t<span class=\"img-center\">\n\t\t\t\t<img src=\"https://entertainimg.kbsmedia.co.kr/cms/uploads/CONTENTS_20211218213843_aa8d41e9535a61946a95334e53d1550f_1.jpg\" alt=\"대체 텍스트\">\n\t\t\t</span>\n\t\t</span>\n\t</span></a>\n\t<span class=\"txt\">\n\t\t<span class=\"max-progtit\"><a href=\"https://kstar.kbs.co.kr/list_view.html?idx=180815\">[SBS연예대상]  차은우 \"오늘은 SBS에서 하트~\"</a></span>\n\t</span>","link":"https://kstar.kbs.co.kr/list_view.html?idx=180815","retrieved":1639837113329,"image":"https://entertainimg.kbsmedia.co.kr/cms/uploads/CONTENTS_20211218213843_aa8d41e9535a61946a95334e53d1550f_1.jpg"},{"title":"[SBS연예대상]  이승엽, 유현주 \"편먹고 공치리 로 참석합니다\" (KBS연예 ─ 연예)","contents":"<a href=\"https://kstar.kbs.co.kr/list_view.html?idx=180810\">\t<span class=\"img-box hh\">\n\t\t<span class=\"img-thum\">\n\t\t\t<span class=\"img-center\">\n\t\t\t\t<img src=\"https://entertainimg.kbsmedia.co.kr/cms/uploads/CONTENTS_20211218213601_085b298b472bed01600c0b475cb758e0.jpg\" alt=\"대체 텍스트\">\n\t\t\t</span>\n\t\t</span>\n\t</span></a>\n\t<span class=\"txt\">\n\t\t<span class=\"max-progtit\"><a href=\"https://kstar.kbs.co.kr/list_view.html?idx=180810\">[SBS연예대상]  이승엽, 유현주 \"편먹고 공치리 로 참석합니다\"</a></span>\n\t</span>","link":"https://kstar.kbs.co.kr/list_view.html?idx=180810","retrieved":1639837113329,"image":"https://entertainimg.kbsmedia.co.kr/cms/uploads/CONTENTS_20211218213601_085b298b472bed01600c0b475cb758e0.jpg"},{"title":"[SBS연예대상] 집사부일체 \"파이팅!\" (KBS연예 ─ 연예)","contents":"<a href=\"https://kstar.kbs.co.kr/list_view.html?idx=180803\">\t<span class=\"img-box hh\">\n\t\t<span class=\"img-thum\">\n\t\t\t<span class=\"img-center\">\n\t\t\t\t<img src=\"https://entertainimg.kbsmedia.co.kr/cms/uploads/CONTENTS_20211218213335_253f1243f202c2ebce9bdf98667adb52.jpg\" alt=\"대체 텍스트\">\n\t\t\t</span>\n\t\t</span>\n\t</span></a>\n\t<span class=\"txt\">\n\t\t<span class=\"max-progtit\"><a href=\"https://kstar.kbs.co.kr/list_view.html?idx=180803\">[SBS연예대상] 집사부일체 \"파이팅!\"</a></span>\n\t</span>","link":"https://kstar.kbs.co.kr/list_view.html?idx=180803","retrieved":1639837113330,"image":"https://entertainimg.kbsmedia.co.kr/cms/uploads/CONTENTS_20211218213335_253f1243f202c2ebce9bdf98667adb52.jpg"},{"title":"[SBS연예대상]  런닝맨 \"시상식의 왕, 유재석은 올해 불참!\" (KBS연예 ─ 연예)","contents":"<a href=\"https://kstar.kbs.co.kr/list_view.html?idx=180791\">\t<span class=\"img-box hh\">\n\t\t<span class=\"img-thum\">\n\t\t\t<span class=\"img-center\">\n\t\t\t\t<img src=\"https://entertainimg.kbsmedia.co.kr/cms/uploads/CONTENTS_20211218212907_ace87bb795b2135923b78b26e8139491.jpg\" alt=\"대체 텍스트\">\n\t\t\t</span>\n\t\t</span>\n\t</span></a>\n\t<span class=\"txt\">\n\t\t<span class=\"max-progtit\"><a href=\"https://kstar.kbs.co.kr/list_view.html?idx=180791\">[SBS연예대상]  런닝맨 \"시상식의 왕, 유재석은 올해 불참!\"</a></span>\n\t</span>","link":"https://kstar.kbs.co.kr/list_view.html?idx=180791","retrieved":1639830721712,"image":"https://entertainimg.kbsmedia.co.kr/cms/uploads/CONTENTS_20211218212907_ace87bb795b2135923b78b26e8139491.jpg"},{"title":"[SBS연예대상]  '동상이몽2 너는 내 운명' 포토타임 (KBS연예 ─ 연예)","contents":"<a href=\"https://kstar.kbs.co.kr/list_view.html?idx=180777\">\t<span class=\"img-box hh\">\n\t\t<span class=\"img-thum\">\n\t\t\t<span class=\"img-center\">\n\t\t\t\t<img src=\"https://entertainimg.kbsmedia.co.kr/cms/uploads/CONTENTS_20211218210519_675f91272b8b7c31a4b1b803ac333f83.jpg\" alt=\"대체 텍스트\">\n\t\t\t</span>\n\t\t</span>\n\t</span></a>\n\t<span class=\"txt\">\n\t\t<span class=\"max-progtit\"><a href=\"https://kstar.kbs.co.kr/list_view.html?idx=180777\">[SBS연예대상]  '동상이몽2 너는 내 운명' 포토타임</a></span>\n\t</span>","link":"https://kstar.kbs.co.kr/list_view.html?idx=180777","retrieved":1639830721715,"image":"https://entertainimg.kbsmedia.co.kr/cms/uploads/CONTENTS_20211218210519_675f91272b8b7c31a4b1b803ac333f83.jpg"},{"title":"[SBS연예대상] 골 때리는 그녀들 \"목표는 승리의 트로피\" (KBS연예 ─ 연예)","contents":"<a href=\"https://kstar.kbs.co.kr/list_view.html?idx=180765\">\t<span class=\"img-box hh\">\n\t\t<span class=\"img-thum\">\n\t\t\t<span class=\"img-center\">\n\t\t\t\t<img src=\"https://entertainimg.kbsmedia.co.kr/cms/uploads/CONTENTS_20211218205508_255669b44e2b8812588601589b9d263f.jpg\" alt=\"대체 텍스트\">\n\t\t\t</span>\n\t\t</span>\n\t</span></a>\n\t<span class=\"txt\">\n\t\t<span class=\"max-progtit\"><a href=\"https://kstar.kbs.co.kr/list_view.html?idx=180765\">[SBS연예대상] 골 때리는 그녀들 \"목표는 승리의 트로피\"</a></span>\n\t</span>","link":"https://kstar.kbs.co.kr/list_view.html?idx=180765","retrieved":1639830721716,"image":"https://entertainimg.kbsmedia.co.kr/cms/uploads/CONTENTS_20211218205508_255669b44e2b8812588601589b9d263f.jpg"},{"title":"[SBS연예대상] 이승기, 장도연, 한혜진 \"오늘의 MC!\" (KBS연예 ─ 연예)","contents":"<a href=\"https://kstar.kbs.co.kr/list_view.html?idx=180747\">\t<span class=\"img-box hh\">\n\t\t<span class=\"img-thum\">\n\t\t\t<span class=\"img-center\">\n\t\t\t\t<img src=\"https://entertainimg.kbsmedia.co.kr/cms/uploads/CONTENTS_20211218204510_92b8bc9c93aaefa19888c0ad327e43ce.jpg\" alt=\"대체 텍스트\">\n\t\t\t</span>\n\t\t</span>\n\t</span></a>\n\t<span class=\"txt\">\n\t\t<span class=\"max-progtit\"><a href=\"https://kstar.kbs.co.kr/list_view.html?idx=180747\">[SBS연예대상] 이승기, 장도연, 한혜진 \"오늘의 MC!\"</a></span>\n\t</span>","link":"https://kstar.kbs.co.kr/list_view.html?idx=180747","retrieved":1639830721718,"image":"https://entertainimg.kbsmedia.co.kr/cms/uploads/CONTENTS_20211218204510_92b8bc9c93aaefa19888c0ad327e43ce.jpg"},{"title":"네이버 바이브  \"종합 오디오 서비스로~\" (KBS연예 ─ 연예)","contents":"<a href=\"https://kstar.kbs.co.kr/list_view.html?idx=180654\">\t<span class=\"img-box hh\">\n\t\t<span class=\"img-thum\">\n\t\t\t<span class=\"img-center\">\n\t\t\t\t<img src=\"https://entertainimg.kbsmedia.co.kr/cms/uploads/CONTENTS_20211218062735_899a7898b213ad7606149e06cf09ba1f_1.png\" alt=\"대체 텍스트\">\n\t\t\t</span>\n\t\t</span>\n\t</span></a>\n\t<span class=\"txt\">\n\t\t<span class=\"max-progtit\"><a href=\"https://kstar.kbs.co.kr/list_view.html?idx=180654\">네이버 바이브  \"종합 오디오 서비스로~\" </a></span>\n\t</span>","link":"https://kstar.kbs.co.kr/list_view.html?idx=180654","retrieved":1639783370322,"image":"https://entertainimg.kbsmedia.co.kr/cms/uploads/CONTENTS_20211218062735_899a7898b213ad7606149e06cf09ba1f_1.png"},{"title":"배우보다 더 배우~ 우리가 ITZY~ (KBS연예 ─ 연예)","contents":"<a href=\"https://kstar.kbs.co.kr/list_view.html?idx=180633\">\t<span class=\"img-box ww\">\n\t\t<span class=\"img-thum\">\n\t\t\t<span class=\"img-center\">\n\t\t\t\t<img src=\"https://entertainimg.kbsmedia.co.kr/cms/uploads/CONTENTS_20211217225106_fd260208f7e0771ff1b13afe79c925c1.PNG\" alt=\"대체 텍스트\">\n\t\t\t</span>\n\t\t</span>\n\t</span></a>\n\t<span class=\"txt\">\n\t\t<span class=\"max-progtit\"><a href=\"https://kstar.kbs.co.kr/list_view.html?idx=180633\">배우보다 더 배우~ 우리가 ITZY~</a></span>\n\t\t<em class=\"prog\"><a href=\"https://kstar.kbs.co.kr/list.html?program_title=2021%20KBS%20%EA%B0%80%EC%9A%94%EB%8C%80%EC%B6%95%EC%A0%9C\">2021 KBS 가요대축제</a></em>\n\t</span>","link":"https://kstar.kbs.co.kr/list_view.html?idx=180633","retrieved":1639750750163,"image":"https://entertainimg.kbsmedia.co.kr/cms/uploads/CONTENTS_20211217225106_fd260208f7e0771ff1b13afe79c925c1.PNG"},{"title":"에스파는 나야~ '가요대축제' 접수한 'Savage' (KBS연예 ─ 연예)","contents":"<a href=\"https://kstar.kbs.co.kr/list_view.html?idx=180627\">\t<span class=\"img-box hh\">\n\t\t<span class=\"img-thum\">\n\t\t\t<span class=\"img-center\">\n\t\t\t\t<img src=\"https://entertainimg.kbsmedia.co.kr/cms/uploads/CONTENTS_20211217224209_c61a1d050ed221441b41de23a7e98305_1.PNG\" alt=\"대체 텍스트\">\n\t\t\t</span>\n\t\t</span>\n\t</span></a>\n\t<span class=\"txt\">\n\t\t<span class=\"max-progtit\"><a href=\"https://kstar.kbs.co.kr/list_view.html?idx=180627\">에스파는 나야~ '가요대축제' 접수한 'Savage'</a></span>\n\t\t<em class=\"prog\"><a href=\"https://kstar.kbs.co.kr/list.html?program_title=2021%20KBS%20%EA%B0%80%EC%9A%94%EB%8C%80%EC%B6%95%EC%A0%9C\">2021 KBS 가요대축제</a></em>\n\t</span>","link":"https://kstar.kbs.co.kr/list_view.html?idx=180627","retrieved":1639750750163,"image":"https://entertainimg.kbsmedia.co.kr/cms/uploads/CONTENTS_20211217224209_c61a1d050ed221441b41de23a7e98305_1.PNG"},{"title":"ITZY부터 아이브까지, 대세 걸그룹 멤버들의 콜라보 F9의 탄생! (KBS연예 ─ 연예)","contents":"<a href=\"https://kstar.kbs.co.kr/list_view.html?idx=180622\">\t<span class=\"img-box ww\">\n\t\t<span class=\"img-thum\">\n\t\t\t<span class=\"img-center\">\n\t\t\t\t<img src=\"https://entertainimg.kbsmedia.co.kr/cms/uploads/CONTENTS_20211217223831_60946d12fbef34aa08221383897f2f07.PNG\" alt=\"대체 텍스트\">\n\t\t\t</span>\n\t\t</span>\n\t</span></a>\n\t<span class=\"txt\">\n\t\t<span class=\"max-progtit\"><a href=\"https://kstar.kbs.co.kr/list_view.html?idx=180622\">ITZY부터 아이브까지, 대세 걸그룹 멤버들의 콜라보 F9의 탄생!</a></span>\n\t\t<em class=\"prog\"><a href=\"https://kstar.kbs.co.kr/list.html?program_title=2021%20KBS%20%EA%B0%80%EC%9A%94%EB%8C%80%EC%B6%95%EC%A0%9C\">2021 KBS 가요대축제</a></em>\n\t</span>","link":"https://kstar.kbs.co.kr/list_view.html?idx=180622","retrieved":1639750750163,"image":"https://entertainimg.kbsmedia.co.kr/cms/uploads/CONTENTS_20211217223831_60946d12fbef34aa08221383897f2f07.PNG"},{"title":"무한확장 NCT U, 터프한 매력으로 휘어잡는 '유니버스' (KBS연예 ─ 연예)","contents":"<a href=\"https://kstar.kbs.co.kr/list_view.html?idx=180616\">\t<span class=\"img-box hh\">\n\t\t<span class=\"img-thum\">\n\t\t\t<span class=\"img-center\">\n\t\t\t\t<img src=\"https://entertainimg.kbsmedia.co.kr/cms/uploads/CONTENTS_20211217222401_b5ffac6bb38852a5236b66b97f39412e.PNG\" alt=\"대체 텍스트\">\n\t\t\t</span>\n\t\t</span>\n\t</span></a>\n\t<span class=\"txt\">\n\t\t<span class=\"max-progtit\"><a href=\"https://kstar.kbs.co.kr/list_view.html?idx=180616\">무한확장 NCT U, 터프한 매력으로 휘어잡는 '유니버스'</a></span>\n\t\t<em class=\"prog\"><a href=\"https://kstar.kbs.co.kr/list.html?program_title=2021%20KBS%20%EA%B0%80%EC%9A%94%EB%8C%80%EC%B6%95%EC%A0%9C\">2021 KBS 가요대축제</a></em>\n\t</span>","link":"https://kstar.kbs.co.kr/list_view.html?idx=180616","retrieved":1639747545531,"image":"https://entertainimg.kbsmedia.co.kr/cms/uploads/CONTENTS_20211217222401_b5ffac6bb38852a5236b66b97f39412e.PNG"},{"title":"스트레이키즈, 남한산성 앞에서 선보인 터프한 퍼포먼스 (KBS연예 ─ 연예)","contents":"<a href=\"https://kstar.kbs.co.kr/list_view.html?idx=180609\">\t<span class=\"img-box ww\">\n\t\t<span class=\"img-thum\">\n\t\t\t<span class=\"img-center\">\n\t\t\t\t<img src=\"https://entertainimg.kbsmedia.co.kr/cms/uploads/CONTENTS_20211217220704_0c29774c32c92a3acbdddd3ea16e16b4_1.PNG\" alt=\"대체 텍스트\">\n\t\t\t</span>\n\t\t</span>\n\t</span></a>\n\t<span class=\"txt\">\n\t\t<span class=\"max-progtit\"><a href=\"https://kstar.kbs.co.kr/list_view.html?idx=180609\">스트레이키즈, 남한산성 앞에서 선보인 터프한 퍼포먼스</a></span>\n\t\t<em class=\"prog\"><a href=\"https://kstar.kbs.co.kr/list.html?program_title=2021%20KBS%20%EA%B0%80%EC%9A%94%EB%8C%80%EC%B6%95%EC%A0%9C\">2021 KBS 가요대축제</a></em>\n\t</span>","link":"https://kstar.kbs.co.kr/list_view.html?idx=180609","retrieved":1639747545536,"image":"https://entertainimg.kbsmedia.co.kr/cms/uploads/CONTENTS_20211217220704_0c29774c32c92a3acbdddd3ea16e16b4_1.PNG"},{"title":"오마이걸, 문화재와 '던 던 댄스~' 춤을 춰! (KBS연예 ─ 연예)","contents":"<a href=\"https://kstar.kbs.co.kr/list_view.html?idx=180604\">\t<span class=\"img-box hh\">\n\t\t<span class=\"img-thum\">\n\t\t\t<span class=\"img-center\">\n\t\t\t\t<img src=\"https://entertainimg.kbsmedia.co.kr/cms/uploads/CONTENTS_20211217220459_48e2fde021f8f1f2b3fae3f8a9bbeb33_1.PNG\" alt=\"대체 텍스트\">\n\t\t\t</span>\n\t\t</span>\n\t</span></a>\n\t<span class=\"txt\">\n\t\t<span class=\"max-progtit\"><a href=\"https://kstar.kbs.co.kr/list_view.html?idx=180604\">오마이걸, 문화재와 '던 던 댄스~' 춤을 춰!</a></span>\n\t\t<em class=\"prog\"><a href=\"https://kstar.kbs.co.kr/list.html?program_title=2021%20KBS%20%EA%B0%80%EC%9A%94%EB%8C%80%EC%B6%95%EC%A0%9C\">2021 KBS 가요대축제</a></em>\n\t</span>","link":"https://kstar.kbs.co.kr/list_view.html?idx=180604","retrieved":1639747545537,"image":"https://entertainimg.kbsmedia.co.kr/cms/uploads/CONTENTS_20211217220459_48e2fde021f8f1f2b3fae3f8a9bbeb33_1.PNG"},{"title":"비투비 민혁, 코로나 확진 탓 백신 미접종→\"새 감염원 발행 가능有\" [전문] (MBC 연예 ─ 아이돌)","contents":"<a href=\"/News/RetrieveNewsInfo/333819\">        <img src=\"//talkimg.imbc.com/TVianUpload/tvian/TViews/image/2021/12/20/t9w7FOcy9K5B637756235352832065.jpg\" alt=\"비투비 민혁, 코로나 확진 탓 백신 미접종→\" 새=\"\" 감염원=\"\" 발행=\"\" 가능有\"=\"\" [전문]\"=\"\">        <div class=\"text-box\">            <p class=\"summary\">비투비 민혁, 코로나 확진 탓 백신 미접종→\"새 감염원 발행 가능有\" [전문]</p>        </div>    </a>","link":"http://enews.imbc.com/News/RetrieveNewsInfo/333819","retrieved":1639995838553,"image":"http://talkimg.imbc.com/TVianUpload/tvian/TViews/image/2021/12/20/t9w7FOcy9K5B637756235352832065.jpg"},{"title":"\"과자값 나오겠네\" 방탄소년단 뷔, 악성 유튜버 고소 예고 (MBC 연예 ─ 아이돌)","contents":"<a href=\"/News/RetrieveNewsInfo/333816\">        <img src=\"//talkimg.imbc.com/TVianUpload/tvian/TViews/image/2021/12/20/9405f3cf-d2c8-49d4-a136-6dacba12a00c.jpg\" alt=\"\" 과자값=\"\" 나오겠네\"=\"\" 방탄소년단=\"\" 뷔,=\"\" 악성=\"\" 유튜버=\"\" 고소=\"\" 예고\"=\"\">        <div class=\"text-box\">            <p class=\"summary\">\"과자값 나오겠네\" 방탄소년단 뷔, 악성 유튜버 고소 예고</p>        </div>    </a>","link":"http://enews.imbc.com/News/RetrieveNewsInfo/333816","retrieved":1639992201525,"image":"http://talkimg.imbc.com/TVianUpload/tvian/TViews/image/2021/12/20/9405f3cf-d2c8-49d4-a136-6dacba12a00c.jpg"},{"title":"송가인·임영웅→MC 이준호 '2021 MBC 가요대제전' 라인업 공개 (MBC 연예 ─ 아이돌)","contents":"<a href=\"/News/RetrieveNewsInfo/333812\">        <img src=\"//talkimg.imbc.com/TVianUpload/tvian/TViews/image/2021/12/20/28ce6ddf-6787-43fe-b4f1-59ed0ec51924.jpg\" alt=\"송가인·임영웅→MC 이준호 '2021 MBC 가요대제전' 라인업 공개\">        <div class=\"text-box\">            <p class=\"summary\">송가인·임영웅→MC 이준호 '2021 MBC 가요대제전' 라인업 공개</p>        </div>    </a>","link":"http://enews.imbc.com/News/RetrieveNewsInfo/333812","retrieved":1639988915229,"image":"http://talkimg.imbc.com/TVianUpload/tvian/TViews/image/2021/12/20/28ce6ddf-6787-43fe-b4f1-59ed0ec51924.jpg"},{"title":"김재중, 착한 얼굴에 그렇지 못한 근육 [인스타] (MBC 연예 ─ 아이돌)","contents":"<a href=\"/News/RetrieveNewsInfo/333811\">        <img src=\"//talkimg.imbc.com/TVianUpload/tvian/TViews/image/2021/12/20/56f6e537-1c51-4385-8f21-f40d57d99606.jpg\" alt=\"김재중, 착한 얼굴에 그렇지 못한 근육 [인스타]\">        <div class=\"text-box\">            <p class=\"summary\">김재중, 착한 얼굴에 그렇지 못한 근육 [인스타]</p>        </div>    </a>","link":"http://enews.imbc.com/News/RetrieveNewsInfo/333811","retrieved":1639984901199,"image":"http://talkimg.imbc.com/TVianUpload/tvian/TViews/image/2021/12/20/56f6e537-1c51-4385-8f21-f40d57d99606.jpg"},{"title":"'솔로지옥' 규현 \"예상을 뒤집을 초대반전과 뉴페이스 기대해 달라\" (MBC 연예 ─ 아이돌)","contents":"<a href=\"/News/RetrieveNewsInfo/333780\">        <img src=\"//talkimg.imbc.com/TVianUpload/tvian/TViews/image/2021/12/20/4c5fcca4-141e-41b2-b03d-bf75b166f107.jpg\" alt=\"'솔로지옥' 규현 \" 예상을=\"\" 뒤집을=\"\" 초대반전과=\"\" 뉴페이스=\"\" 기대해=\"\" 달라\"\"=\"\">        <div class=\"text-box\">            <p class=\"summary\">'솔로지옥' 규현 \"예상을 뒤집을 초대반전과 뉴페이스 기대해 달라\"</p>        </div>    </a>","link":"http://enews.imbc.com/News/RetrieveNewsInfo/333780","retrieved":1639981592127,"image":"http://talkimg.imbc.com/TVianUpload/tvian/TViews/image/2021/12/20/4c5fcca4-141e-41b2-b03d-bf75b166f107.jpg"},{"title":"'나를 불러줘' 효연, 소녀시대 찐우정 비하인드 대방출 (MBC 연예 ─ 아이돌)","contents":"<a href=\"/News/RetrieveNewsInfo/333767\">        <img src=\"//talkimg.imbc.com/TVianUpload/tvian/TViews/image/2021/12/20/e0c39939-6f99-4112-8ea4-3a1527c9e157.jpg\" alt=\"'나를 불러줘' 효연, 소녀시대 찐우정 비하인드 대방출\">        <div class=\"text-box\">            <p class=\"summary\">'나를 불러줘' 효연, 소녀시대 찐우정 비하인드 대방출</p>        </div>    </a>","link":"http://enews.imbc.com/News/RetrieveNewsInfo/333767","retrieved":1639977666980,"image":"http://talkimg.imbc.com/TVianUpload/tvian/TViews/image/2021/12/20/e0c39939-6f99-4112-8ea4-3a1527c9e157.jpg"},{"title":"'주간아이돌' 연말 결산 특집…에스파→엔하이픈 중 대상 거머쥘 팀 누구? (MBC 연예 ─ 아이돌)","contents":"<a href=\"/News/RetrieveNewsInfo/333762\">        <img src=\"//talkimg.imbc.com/TVianUpload/tvian/TViews/image/2021/12/20/bace4607-4b4f-4d49-af7e-780b042bc2f3.jpg\" alt=\"'주간아이돌' 연말 결산 특집…에스파→엔하이픈 중 대상 거머쥘 팀 누구?\">        <div class=\"text-box\">            <p class=\"summary\">'주간아이돌' 연말 결산 특집…에스파→엔하이픈 중 대상 거머쥘 팀 누구?</p>        </div>    </a>","link":"http://enews.imbc.com/News/RetrieveNewsInfo/333762","retrieved":1639974516593,"image":"http://talkimg.imbc.com/TVianUpload/tvian/TViews/image/2021/12/20/bace4607-4b4f-4d49-af7e-780b042bc2f3.jpg"},{"title":"'방과후 설렘' 최약체 4학년, 최강 3학년 꺾고 1라운드 승리 (MBC 연예 ─ 아이돌)","contents":"<a href=\"/News/RetrieveNewsInfo/333738\">        <img src=\"//talkimg.imbc.com/TVianUpload/tvian/TViews/image/2021/12/20/ca33e418-a9ed-458c-adc9-95a745bccb78.jpg\" alt=\"'방과후 설렘' 최약체 4학년, 최강 3학년 꺾고 1라운드 승리\">        <div class=\"text-box\">            <p class=\"summary\">'방과후 설렘' 최약체 4학년, 최강 3학년 꺾고 1라운드 승리</p>        </div>    </a>","link":"http://enews.imbc.com/News/RetrieveNewsInfo/333738","retrieved":1639962620356,"image":"http://talkimg.imbc.com/TVianUpload/tvian/TViews/image/2021/12/20/ca33e418-a9ed-458c-adc9-95a745bccb78.jpg"},{"title":"방탄소년단, 英 '브릿 어워드' 2년 연속 노미네이트...'인터내셔널 그룹' 수상 후보 (MBC 연예 ─ 아이돌)","contents":"<a href=\"/News/RetrieveNewsInfo/333710\">        <img src=\"//talkimg.imbc.com/TVianUpload/tvian/TViews/image/2021/12/19/oeTRGxjOfpWD637755219014062377.jpg\" alt=\"방탄소년단, 英 '브릿 어워드' 2년 연속 노미네이트...'인터내셔널 그룹' 수상 후보\">        <div class=\"text-box\">            <p class=\"summary\">방탄소년단, 英 '브릿 어워드' 2년 연속 노미네이트...'인터내셔널 그룹' 수상 후보</p>        </div>    </a>","link":"http://enews.imbc.com/News/RetrieveNewsInfo/333710","retrieved":1639895102465,"image":"http://talkimg.imbc.com/TVianUpload/tvian/TViews/image/2021/12/19/oeTRGxjOfpWD637755219014062377.jpg"},{"title":"권은비, 첫 팬미팅 성료 \"루비 덕분에 많은 힘 받아\" (MBC 연예 ─ 아이돌)","contents":"<a href=\"/News/RetrieveNewsInfo/333708\">        <img src=\"//talkimg.imbc.com/TVianUpload/tvian/TViews/image/2021/12/19/f1VNNXSbSVR3637755133854868119.JPG\" alt=\"권은비, 첫 팬미팅 성료 \" 루비=\"\" 덕분에=\"\" 많은=\"\" 힘=\"\" 받아\"\"=\"\">        <div class=\"text-box\">            <p class=\"summary\">권은비, 첫 팬미팅 성료 \"루비 덕분에 많은 힘 받아\"</p>        </div>    </a>","link":"http://enews.imbc.com/News/RetrieveNewsInfo/333708","retrieved":1639888063472,"image":"http://talkimg.imbc.com/TVianUpload/tvian/TViews/image/2021/12/19/f1VNNXSbSVR3637755133854868119.JPG"},{"title":"'아는 형님' 최예나, 제기차기로 '홈런'→이수근 \"너만 방송 나올 거야?\" (MBC 연예 ─ 아이돌)","contents":"<a href=\"/News/RetrieveNewsInfo/333704\">        <img src=\"//talkimg.imbc.com/TVianUpload/tvian/TViews/image/2021/12/19/UrmO4q7zA5Pq637755114219812653.jpg\" alt=\"'아는 형님' 최예나, 제기차기로 '홈런'→이수근 \" 너만=\"\" 방송=\"\" 나올=\"\" 거야?\"\"=\"\">        <div class=\"text-box\">            <p class=\"summary\">'아는 형님' 최예나, 제기차기로 '홈런'→이수근 \"너만 방송 나올 거야?\"</p>        </div>    </a>","link":"http://enews.imbc.com/News/RetrieveNewsInfo/333704","retrieved":1639884168780,"image":"http://talkimg.imbc.com/TVianUpload/tvian/TViews/image/2021/12/19/UrmO4q7zA5Pq637755114219812653.jpg"},{"title":"노을 \"2년 만에 관객 만나 행복\" 서울 공연 성료 (다음 연예 ─ 뉴스 ─ 뮤직)","contents":"[동아닷컴] 그룹 노을이 관객들의 뜨거운 박수 속에 서울 공연을 마쳤다. 노을이 지난 금요일부터 3일간(17-19일) 코엑스 오디토리움에서 열린 2021 전국투어 콘서트 '노을이 내린 밤'으로 서울 관객들과 만났다. 코로나19로 2년만에 열린 콘서트에 3일 공연 모두 매진을 기록하는 등 공연 전부터 큰 기대를 모았던 만큼 관객들과 함께 최고의 공연을 함께","link":"https://entertain.v.daum.net/v/20211221023010741","retrieved":1640024801566},{"title":"나태주 오늘 생일..트롯픽 이벤트 주인공 (다음 연예 ─ 뉴스 ─ 뮤직)","contents":"[동아닷컴]   나태주 오늘(21일) 생일…트롯픽 이벤트 주인공 [DA:차트] 가수 나태주가 트롯픽 생일 이벤트를 받는다. 21일 트롯 문화를 사랑하는 사람들을 응원하는 서비스 트롯픽(trotpick)에 따르면 나태주는 12월 생일자를 대상으로 한 스페셜 투표에서 이벤트 주인공으로 선정됐다. 이번 투표는 지난달 15일부터 21일까지 진행됐다. 트롯픽의 생","link":"https://entertain.v.daum.net/v/20211221000023037","retrieved":1640013790282},{"title":"윤하 '별의 조각', 美빌보드 선정 올해의 베스트 K팝 (다음 연예 ─ 뉴스 ─ 뮤직)","contents":"[동아닷컴] [사진 = C9엔터테인먼트 제공]가수 윤하가 미국 타임지에 이어 빌보드의 극찬을 받았다. 윤하의 정규 6집 'END THEORY(엔드 띠어리)'의 타이틀곡 '별의 조각'은 지난 17일(현지시간) 미국 음악 전문 매체 빌보드(Billboard) 공식 홈페이지에서 '평론가들이 뽑은 2021년 베스트 K-팝 노래 25곡(25 Best K-Pop","link":"https://entertain.v.daum.net/v/20211221000014031","retrieved":1640013790282},{"title":"임영웅 팬클럽, 대규모 지하철 광고로 KBS 단독쇼 'We're HERO' 응원 (다음 연예 ─ 뉴스 ─ 뮤직)","contents":"(엑스포츠뉴스 이정범 기자) 임영웅 팬클럽에서 임영웅의 생애 첫 지상파 단독 콘서트를 기념하여 홍보 광고를 진행한다. 12월 26일 일요일 밤 9시 15분에 방송될 ‘KBS 송년특집 We're HERO 임영웅’은 &nbsp;지난 12월 10일 고양 킨텍스에서 무사히 녹화를 마쳤다. 이번 단독쇼는 100:1의 경쟁률을 뚫고 전국에서 초대된 495명의 관객과 함께 했다","link":"https://entertain.v.daum.net/v/20211221000004020","retrieved":1640013790283},{"title":"포레스텔라 고우림, 現소속사와 개인 전속계약도 체결 (다음 연예 ─ 뉴스 ─ 뮤직)","contents":"크로스오버 그룹 포레스텔라 멤버 고우림이 솔로 활동도 비트인터렉티브와 함께한다. 20일 비트인터렉티브는 \"고우림과 최근 전속계약을 체결했다. 포레스텔라 활동은 물론, 솔로 아티스트로서도 고우림이 다방면에서 음악 팬들의 큰 사랑을 받을 수 있도록 전폭적으로 지원하겠다\"고 밝혔다. 지난 8월부터 포레스텔라의 음악, 방송, 글로벌 매니지먼트 및 음악 제작","link":"https://entertain.v.daum.net/v/20211220232211752","retrieved":1640013790283},{"title":"'너목보' 1월 29일 '9번째 시즌'으로 컴백 (다음 연예 ─ 뉴스 ─ 뮤직)","contents":"'너의 목소리가 보여'가 9번째 시즌을 선보인다. 대반전 음악 추리쇼 Mnet ‘너의 목소리가 보여'는 내달 29일 새로운 시즌 첫 방송을 확정했다. '너의 목소리가 보여'는 직업과 나이, 노래 실력을 숨긴 미스터리 싱어들 중 몇 가지 단서만으로 실력자와 음치를 가려내는 대반전 음악 추리쇼 프로그램이다. 2015년 처음 방영한 이후 황치열, 멜로망스","link":"https://entertain.v.daum.net/v/20211220232016736","retrieved":1640013790283},{"title":"트와이스 정연, 월드투어 서울 공연 불참 \"건강상 사유\" (다음 연예 ─ 뉴스 ─ 뮤직)","contents":"트와이스 정연이 서울 공연에 불참한다. JYP엔터테인먼트(이하 JYP) 측은 20일 트와이스 공식 팬 커뮤니티를 통해 멤버 정연의 TWICE 4TH WORLD TOUR 'Ⅲ' 서울 공연 불참 관련 소식을 전했다. JYP 측은 \"25일과 26일 양일간 진행되는 TWICE 4TH WORLD TOUR 'Ⅲ' 서울 공연에 멤버 정연이 건강상의 사유로 인해 본","link":"https://entertain.v.daum.net/v/20211220220410190","retrieved":1640007074330},{"title":"\"설레는 마음\" 있지, 22일 日정식데뷔..쇼케이스 뜨거운 열기 (다음 연예 ─ 뉴스 ─ 뮤직)","contents":"K팝 4세대 걸그룹' ITZY(있지)가 일본 데뷔 온라인 쇼케이스를 통해 팬심을 뜨겁게 예열했다. ITZY는 오는 22일 베스트 앨범 'IT'z ITZY'(잇츠 있지)를 발매하고 일본에서 정식 데뷔를 맞이한다. 앞서 지난달 1일 'WANNABE'(워너비) 일본어 버전, 이달 1일 'LOCO'(로꼬) 일본어 버전을 선공개하고 열기를 더했다. 특히 지난달","link":"https://entertain.v.daum.net/v/20211220213433852","retrieved":1640003705343},{"title":"임영웅 팬클럽 '웅바라기스쿨' 사랑의 달팽이에 608만원 기부·버스 광고 \"KBS 단독쇼 축하합니다\" (다음 연예 ─ 뉴스 ─ 뮤직)","contents":"[스타뉴스 문완식 기자] 가수 임영웅의 팬들이 KBS 단독쇼를 축하하며 청각장애인들을 위한 기부로 의미를 더했다. 임영웅 팬클럽 영웅시대 '웅바라기스쿨'은 12월 17일 임영웅의 KBS 단독쇼 방송을 축하하며 청각장애인을 지원하는 사단법인 사랑의 달팽이에 임영웅 이름으로 기부금 608만 원을 전달했다. '웅바라기스쿨'은 \"임영웅 가수의 선한 영향력에 동","link":"https://entertain.v.daum.net/v/20211220210002466","retrieved":1640003705347},{"title":"이런 외계요정은 처음이야.. 록킹돌 메이킹 (다음 연예 ─ 뉴스 ─ 뮤직)","contents":"뮤직비디오 촬영이 한창인 록킹돌 로아[이데일리 스타in 윤기백 기자] [스타in X 록킹돌]은 SRP엔터테인먼트 신인 걸그룹 록킹돌(Rocking doll)을 소개하는 코너입니다. ‘탈지구급 신인’ 록킹돌이 드디어 가요계에 상륙했습니다. 록킹돌은 SRP엔터테인먼트가 처음으로 론칭하는 1호 걸그룹인데요. 빼어난 미모와 출중한 실력 그리고 독보적인 외계요정","link":"https://entertain.v.daum.net/v/20211220202339035","retrieved":1640003705347},{"title":"지세희, 한중 연예인 컬링대회 '하드캐리'한 운동능력자..\"희열 이루 말할 수 없다\" (다음 연예 ─ 뉴스 ─ 뮤직)","contents":"[OSEN=최나영 기자] 가수 지세희가 한-중 연예인 컬링대회에서 맹활약하며 팀을 우승으로 이끌었다. 2022년 북경동계올림픽 성공을 기원하고 한중수교 30주년을 기념하며 '한-중 연예인 컬링대회'에서&nbsp;지세희는 팀 '빙나이다' 소속으로 인순이, 레인보우 출신 배우 고우리, 트로트 가수 우현정, 싱어송라이터 겸 보컬트레이너 쏘킴, 스포츠모델 겸 방송인 김정화","link":"https://entertain.v.daum.net/v/20211220192854379","retrieved":1639999126079},{"title":"비투비 이민혁 측 \"코로나19 음성, 백신 접종 완료 못 해 자가격리\" (다음 연예 ─ 뉴스 ─ 뮤직)","contents":"(엑스포츠뉴스 김유진 기자) 그룹 비투비 이민혁이 신종 코로나바이러스 감염증(코로나19) 음성 판정을 받았지만 자가격리에 들어간다. 20일 이민혁의 소속사 큐브엔터테인먼트는 \"이민혁이 스케줄 중 코로나19 확진자와 동선이 겹친 사실을 확인해 선제적 차원에서 코로나19 유전자 증폭(PCR) 검사를 진행, 검사 결과 '음성' 판정을 받았다\"고 밝혔다. 이어","link":"https://entertain.v.daum.net/v/20211220184041736","retrieved":1639995845162},{"title":"에스파, S.E.S.와 광야로..'Dreams Come True' 재탄생 (다음 연예 ─ 뉴스 ─ 뮤직)","contents":"[동아닷컴] 그룹 S.E.S.의 ‘Dreams Come True’(드림스 컴 트루)가 그룹 에스파(aespa)의 색깔로 재탄생했다. 20일 오후 6시 공개된 에스파의 ‘Dreams Come True’는 SM엔터테인먼트와 유튜브가 함께 진행하는 ‘리마스터링 프로젝트’의 일환이다. 그룹 S.E.S.가 1998년 발표한 정규 2집 타이틀 곡을 재해석, 에스","link":"https://entertain.v.daum.net/v/20211220182446466","retrieved":1639995845163},{"title":"몽환적 분위기에 힙 한스푼..에스파의 'Dreams Come True' (다음 연예 ─ 뉴스 ─ 뮤직)","contents":"[스타뉴스 공미나 기자] /사진=뮤직비디오 캡처그룹 에스파(aespa)가 S.E.S.의 명곡을 재해석했다. 에스파는 20일 오후 6시 '드림스 컴 트루 (Dreams Come True)' 음원과 뮤직비디오를 공개했다. 1998년 발표한 S.E.S. 정규 2집 타이틀곡을 재해석한 이번 곡은 SM과 유튜브가 함께 진행하는 '리마스터링 프로젝트'의 일환으로 선","link":"https://entertain.v.daum.net/v/20211220182109394","retrieved":1639992206900},{"title":"1415 \"英 'BBC 뮤직어워드' 목표, 영어 연습 더 하면..\" (다음 연예 ─ 뉴스 ─ 뮤직)","contents":"(엑스포츠뉴스 이슬 기자) ([엑's 인터뷰①]에 이어)&nbsp;인디 팝 듀오 1415가 영국 'BBC 뮤직어워드'가 목표라고 밝혔다. 지난 8일 세 번째 EP 'naps!(냅스)'를 발매한 1415는 최근 엑스포츠뉴스와 만나 두 사람의 첫 만남, 앞으로의 계획 등에 대한 이야기를 나눴다. 약 7년 동안 함께 살고 있는 1415는 생활 속에서 자연스럽게 곡을 만들","link":"https://entertain.v.daum.net/v/20211220181002209","retrieved":1639992206900},{"title":"\"현실이 드라마 반영한다는 반응 가장 인상 깊었다\" (다음 연예 ─ 뉴스 ─ 스타)","contents":"‘진짜 정치판’을 옮겨다 놓은 것 같은 싱크로율을 보이면서도 비판보다 풍자와 재미에 집중한 웨이브 오리지널 웹드라마 ‘이렇게 된 이상 청와대로 간다’(이상청)는 지난달 12일 웨이브에서 전편이 공개된 후 시청자의 큰 호응을 얻었다. 이 드라마를 기획한 송편 크리에이터는 20일 국민일보와 서면 인터뷰에서 “‘드라마가 현실을 반영하는 게 아니라 현실이 드라마를","link":"https://entertain.v.daum.net/v/20211221040905141","retrieved":1640027916831},{"title":"'동상이몽2' 이현이, \"이 우정 장례식까지 가자\"..수현→지소연 '슈퍼모델 동기'들과 특별한 만남 (다음 연예 ─ 뉴스 ─ 스타)","contents":"[SBS연예뉴스 | 김효정 에디터] 이현이가 슈퍼모델 동기들과 특별한 시간을 가졌다. 20일 방송된 SBS '동상이몽 시즌2-너는 내 운명'(이하 '동상이몽2')에서는 이현이 홍성기 부부의 일상이 공개됐다. 이날 방송에서 이현이는 슈퍼모델 동기인 배우 수현, 배우 지소연, 그리고 그의 남편 송재희까지 함께 특별한 모임을 준비했다. 이들은 이날 최근 결혼한","link":"https://entertain.v.daum.net/v/20211221030601949","retrieved":1640024807781},{"title":"'동상이몽2' 홍성기♥이현이, 배우 지소연 활약으로 '연애 시작'..비하인드 스토리 공개 (다음 연예 ─ 뉴스 ─ 스타)","contents":"[SBS연예뉴스 | 김효정 에디터] 홍성기가 이현이와 연애를 시작하게 된 계기를 밝혔다. 20일 방송된 SBS '동상이몽 시즌2-너는 내 운명'(이하 '동상이몽2')에서는 이현이 홍성기 부부의 일상이 공개됐다. 이날 방송에서 홍성기는 본인과 이현이가 사귀게 된 계기가 배우 지소연이라고 밝혀 모두의 관심을 모았다. 그는 \"11년 전 현이의 생일날이었다. 그때","link":"https://entertain.v.daum.net/v/20211221022101727","retrieved":1640021358834},{"title":"'동상이몽2' 김윤지, 1주일 5kg 감량 꿀팁..'다이어트 10계명' 공개 (다음 연예 ─ 뉴스 ─ 스타)","contents":"[SBS연예뉴스 | 김효정 에디터] 김윤지가 1주일 5kg 감량 꿀팁을 공개했다. 20일 방송된 SBS '동상이몽 시즌2-너는 내 운명'(이하 '동상이몽2')에서는 다이어트에 도전하는 김윤지 최우성 부부의 모습이 그려졌다. 이날 방송에서 김윤지는 프로필 사진 촬영을 위해 다이어트 돌입했다. 본격적인 다이어트에 앞서 김윤지는 1주일에 5kg 감량 비법이 있다","link":"https://entertain.v.daum.net/v/20211221014800688","retrieved":1640021358835},{"title":"'동상이몽2' 수현, 재미교포 사업가 남편과의 달달한 러브 스토리 공개 (다음 연예 ─ 뉴스 ─ 스타)","contents":"[스포츠서울 | 남서영기자]배우 수현이 재미교포 사업가 남편과의 러브 스토리를 공개했다. 20일 방송된 SBS ‘동상이몽2-너는 내 운명’에서는 수현과 재미교포 사업가 남편의 러브 스토리가 공개됐다. 이날 모델 이현이는 배우 수현과 지소연, 사업가 이유정과 만났다. 2년간 남편과 친구로 지냈다 연인 관계로 발전했다는 수현은 “해","link":"https://entertain.v.daum.net/v/20211221011313565","retrieved":1640018116052},{"title":"'동상이몽2' 김구라와 동갑 조은숙 \"2살 연하 남편, 아직도 애기라고 불러\" (다음 연예 ─ 뉴스 ─ 스타)","contents":"[SBS연예뉴스 | 김효정 에디터] 조은숙이 남편에 대한 애정을 드러냈다. 20일 방송된 SBS '동상이몽 시즌2-너는 내 운명'(이하 '동상이몽2')에서는 배우 조은숙이 스페셜 MC로 등장했다. 이날 방송에서는 26년 차 배우 조은숙이 오랜만에 예능에 출연해 눈길을 끌었다. 그의 등장에 김숙은 \"20년 전에 봤는데 여고괴담 속 2등 귀신처럼 똑같은 모습이","link":"https://entertain.v.daum.net/v/20211221010901558","retrieved":1640018116053},{"title":"'동상이몽2' 이현이, 모델 동기 수현X지소연X이유정과 '깜짝 회동' (다음 연예 ─ 뉴스 ─ 스타)","contents":"'동상이몽2' 이현이가 모델 절친들을 만났다. 20일 방송된 SBS 예능프로그램 '동상이몽2- 너는 내 운명'(이하 '동상이몽2')에서는 이현이는 같은 모델 기수였던 배우 수현, 배우 지소연, 이유정과 회동을 가지는 모습이 그려졌다. 이날 스페셜 MC로 등장한 배우 조은숙은 \"제가 생각하는 연하는 4~5년은 어려야 연하다\"며 \"당시 남편이 저보다 어","link":"https://entertain.v.daum.net/v/20211221010601541","retrieved":1640018116060},{"title":"'싱어게인2' 조현영, 선미 슈퍼 어게인으로 기사 회생 \"팬으로서 감사해\" (다음 연예 ─ 뉴스 ─ 스타)","contents":"[스포츠투데이 이소연 기자] 조현영이 '싱어게인2'에 슈퍼 어게인으로 통과했다. 20일 오후 방송된 JTBC 예능 프로그램 '싱어게인2'에서는 걸그룹 레인보우 출신 조현영이 57호 가수로 등장했다. 이날 조현영은 \"성대 폴립 수술을 해서 6개월 이상 소리 자체를 낼 수가 없었다. 노래를 해야 하는 상황이 올 때마다 후덜덜 떨리더라. 이제는 부딪혀봐야 할","link":"https://entertain.v.daum.net/v/20211221010411522","retrieved":1640018116062},{"title":"수현 \"♥재미교포 남편 육아 좋아해..부부싸움 無\"→김윤지, 인생 최고 몸무게 '55kg'에 충격 (다음 연예 ─ 뉴스 ─ 스타)","contents":"[스포츠조선 조윤선 기자] 배우 수현이 재미교포 사업가 남편과의 러브 스토리를 최초로 공개했다. 20일 방송된 SBS '동상이몽2-너는 내 운명'에서는 수현과 재미교포 사업가 남편의 러브 스토리, 김윤지의 다이어트 비법이 공개됐다. 이현이는 16년 절친인 배우 수현과 지소연, 사업가 이유정과 만남을 가졌다. 2005년 한중 슈퍼모델 선발대회","link":"https://entertain.v.daum.net/v/20211221005633442","retrieved":1640018116065},{"title":"'결혼 3년차' 수현 \"♥재미교포 남편과 잘 안 싸워.. 잔소리 상상불가\" (다음 연예 ─ 뉴스 ─ 스타)","contents":"'동상이몽2' 수현이 남편에 대한 애정을 드러냈다. 20일 방송된 SBS 예능프로그램 '동상이몽2- 너는 내 운명'(이하 '동상이몽2')에서는 이현이는 같은 모델 기수였던 배우 수현, 배우 지소연과 비밀회동을 가지는 모습이 그려졌다. 이날 이유정은 동기들에 부부 싸움 꿀팀을 물었다. 이에 이현이는 \"나는 친구들한테 하는 얘기인데 싸워봐야 한다고 생각하","link":"https://entertain.v.daum.net/v/20211221004200353","retrieved":1640018116066},{"title":"수현→지소연·송재희, 이현이 부부와 만남..슈퍼모델 동기 절친 (다음 연예 ─ 뉴스 ─ 스타)","contents":"(서울=뉴스1) 박하나 기자 = '동상이몽2'에 배우 수현 지소연 송재희가 출격했다. 20일 오후 방송된 SBS 예능 프로그램 '동상이몽2-너는 내 운명'(이하 '동상이몽2')에서 16년 지기 절친 배우 수현, 지소연, 사업가 이유정과 만난 이현이 홍성기 부부의 모습이 담겼다. 이날 지소연의 남편 배우 송재희도 함께했다. 이현이는 2005년 슈퍼모델 선","link":"https://entertain.v.daum.net/v/20211221003645344","retrieved":1640018116066},{"title":"'동상이몽' 수현 \"사업가 남편, 배려심 넘치고 육아도 좋아해\" (다음 연예 ─ 뉴스 ─ 스타)","contents":"[TV리포트=이혜미 기자] 배우 수현이 남편과 부부싸움을 하지 않는다며 남다른 부부금슬을 뽐냈다. 20일 방송된 SBS ‘동상이몽-너는 내 운명’에선 수현이 출연해 2년차 부부의 러브스토리를 공개했다. 수현은 지난 2019년 재미교포 사업가와 웨딩마치를 울렸다. 이날 수현은 “부부싸움을 하나?”란 질문에 “우린 안 싸운다. 남편이 말이 없는 편이다”라고 답","link":"https://entertain.v.daum.net/v/20211221002830309","retrieved":1640018116067},{"title":"'동상이몽2' 수현, 재미교포 사업가 남편 언급 \"육아 너무 좋아하고 서로 안 싸워\" (다음 연예 ─ 뉴스 ─ 스타)","contents":"[스포츠투데이 이소연 기자] '동상이몽2' 배우 수현이 결혼 3년 차 일상을 고백했다. 20일 방송된 SBS 예능프로그램 '동상이몽2- 너는 내 운명'(이하 '동상이몽2')에서 이현이는 남편 홍성기와 함께 16년 지기 절친인 배우 수현, 지소연, 이유정과 지소연의 남편인 배우 송재희 등 오랜만에 슈퍼모델 동기들과 만남을 가졌다. 결혼 3년 차 수현은 재미교","link":"https://entertain.v.daum.net/v/20211221002811303","retrieved":1640018116067},{"title":"첫방 '한 사람만' 안은진 호스피스 입성..김경남, 서연우 구했다 (다음 연예 ─ 뉴스 ─ 스타)","contents":"(서울=뉴스1) 이지현 기자 = '한 사람만' 안은진이 호스피스에 입성했다. 20일 오후 방송된 JTBC 새 월화드라마 '한 사람만'에서 표인숙(안은진 분)은 뇌종양 판정을 받고 호스피스에서 홀로 생을 마감하기로 마음먹었다. 민우천(김경남 분)은 가정 폭력에 시달리던 하산아(서연우 분)를 구했다. 표인숙은 어려운 가정 형편에도 세신사로 악착 같이 일","link":"https://entertain.v.daum.net/v/20211221002351283","retrieved":1640018116068},{"title":"안은진 '한 사람만', 처연한 인생드라마 (다음 연예 ─ 뉴스 ─ 스타)","contents":"[티브이데일리 이기은 기자] '한 사람만‘이 가슴을 건드리는 처연한 휴먼극의 포문을 열었다. 부모에게 버림 받은 불우한 청춘 안은진이 시한부 선고를 받았다. 20일 밤 JTBC 월화드라마 ‘한 사람만'(극본 문정민 연출 오현종) 첫 방송 1회에서는 등장인물 삶의 마지막을 준비하는 표인숙(안은진), 강세연(강예원), 성미도(박수영) 등의 묘한 인연이 시작됐다","link":"https://entertain.v.daum.net/v/20211221002212275","retrieved":1640013795021},{"title":"덴젤 워싱턴, 배우 은퇴 시사..\"맡을 수 있는 역할 많지 않아\" (다음 연예 ─ 뉴스 ─ 해외)","contents":"(엑스포츠뉴스 이창규 기자) 할리우드 배우 덴젤 워싱턴이 은퇴를 시사했다. 덴젤 워싱턴은 지난 16일(현지시간) 엔터테인먼트 투데이(ET)와의 인터뷰에서 \"이번 작품('맥베스의 비극')의 캐릭터처럼 나도 연기 경력의 끝자락에 와 있다\"며 \"솔직히 말해 연기가 아닌 다른 일을 찾고 있다. 내가 연기를 하는 한 이것은 엄청난 도전일 것\"이라고 밝혔다. 그는","link":"https://entertain.v.daum.net/v/20211220171028541","retrieved":1639988932815},{"title":"임영웅 팬클럽, 대규모 지하철 광고로 KBS 단독쇼 ‘We're HERO’ 응원 (네이버 TV연예 ─ 최신뉴스 ─ 뮤직)","contents":"(엑스포츠뉴스 이정범 기자) 임영웅 팬클럽에서 임영웅의 생애 첫 지상파 단독 콘서트를 기념하여 홍보 광고를 진행한다. 12월 26일 일요일 밤 9시 15분에 방송될 ‘KBS 송년특집 We're HERO 임영웅’은 지","link":"https://entertain.naver.com/now/read?oid=311&aid=0001387736","retrieved":1640013807504},{"title":"안경도 찰떡..임영웅, '안경이 잘 어울리는 스타' (네이버 TV연예 ─ 최신뉴스 ─ 뮤직)","contents":"가수 임영웅이 '안경이 잘 어울리는 스타' 1위에 오르며 존재감을 빛냈다. 임영웅은 팬앤스타 포토톡 12월 3주차 '안경이 잘 어울리는 스타' 투표에서 24만 9336표를 획득, 1위를 차지했다. 1위에 오른 사진","link":"https://entertain.naver.com/now/read?oid=108&aid=0003014254","retrieved":1640013807505},{"title":"온앤오프, 군입대 앞두고 또 한 번 입증한 저력 (네이버 TV연예 ─ 최신뉴스 ─ 뮤직)","contents":"‘명곡 맛집’ 온앤오프(ONF)가 입대를 앞두고 또 한 번 자체 기록을 경신하며 새 앨범 공식 활동을 종료했다. 지난 3일 여섯 번째 미니앨범 ‘Goosebumps’를 발매하며 컴백한 온앤오프는 지난 19일 참석한","link":"https://entertain.naver.com/now/read?oid=410&aid=0000838970","retrieved":1640013807507},{"title":"인디 팝 듀오 1415, 하이앤드 리빙 브랜드와 컬래버…‘naps!’·‘lost’ 어쿠스틱 라이브 공개 (네이버 TV연예 ─ 최신뉴스 ─ 뮤직)","contents":"[스포츠경향] 인디 팝 듀오 1415(주성근, 오지현)가 하이앤드 리빙 브랜드와 컬래버레이션을 펼쳤다. 1415는 지난 19일 공식 SNS를 통해 세 번째 EP ‘naps!(냅스)’의 동명의 타이틀곡과 수록곡 ‘lo","link":"https://entertain.naver.com/now/read?oid=144&aid=0000782171","retrieved":1640013807508},{"title":"임영웅 팬클럽 '웅바라기스쿨' 사랑의 달팽이에 608만원 기부·버스 광고 \"KBS 단독쇼 축하합니다\" (네이버 TV연예 ─ 최신뉴스 ─ 뮤직)","contents":"가수 임영웅의 팬들이 KBS 단독쇼를 축하하며 청각장애인들을 위한 기부로 의미를 더했다. 임영웅 팬클럽 영웅시대 '웅바라기스쿨'은 12월 17일 임영웅의 KBS 단독쇼 방송을 축하하며 청각장애인을 지원하는 사단법인","link":"https://entertain.naver.com/now/read?oid=108&aid=0003014234","retrieved":1640003724842},{"title":"‘해리 포터 시리즈 영화음악 크리스마스 에디션’(Christmas At Hogwarts) 4컬러 4LP 박스세트 발매 (네이버 TV연예 ─ 최신뉴스 ─ 뮤직)","contents":"[스포츠경향] 조앤 롤링 판타지 소설을 영화로 만들어 전세계 관객을 사로 잡았던 ‘해리 포터 시리즈’ 8부작의 음악을 모두 감상할 수 있는 ‘해리 포터 크리스마스 에디션 박스세트 4LP가 발매됐다고 굿인터내셔널 레이","link":"https://entertain.naver.com/now/read?oid=144&aid=0000782151","retrieved":1640003724843},{"title":"하이브, ‘2022 위버스 콘’에서 서태지 헌정 무대 (네이버 TV연예 ─ 최신뉴스 ─ 뮤직)","contents":"[헤럴드경제=고승희 기자] 저스틴 비버부터 세븐틴까지 총출동하는 하이브의 연말 콘서트 ‘2022 위버스 콘 ‘뉴 에라’(2022 Weverse Con ‘New Era’)’에서 서태지 헌정 무대를 선보인다고 하이브가","link":"https://entertain.naver.com/now/read?oid=016&aid=0001927026","retrieved":1639999144207},{"title":"샤이니 민호, '하트브레이크' 뮤비 티저…SF 영상미 (네이버 TV연예 ─ 최신뉴스 ─ 뮤직)","contents":"[서울=뉴시스]안소윤 인턴 기자 = 그룹 '샤이니' 민호의 신곡 뮤직비디오 티저 영상이 공개된다. 20일 오후 9시 민호의 신곡 '하트브레이크(Heartbreak)' 뮤직비디오 티저 영상이 유튜브 SM타운 채널 등에","link":"https://entertain.naver.com/now/read?oid=003&aid=0010899738","retrieved":1639995864765},{"title":"그루비룸 '에어리어', 문화레이블 꿈꾼다…팝업스토어 운영 (네이버 TV연예 ─ 최신뉴스 ─ 뮤직)","contents":"[서울=뉴시스]이재훈 기자 = 프로듀서 팀 '그루비룸'(규정·휘민)이 이끄는 레이블 에어리어(@AREA)가 문화 레이블로 도약을 꿈 꾼다. 20일 에어리어에 따르면, 내년 1월 13일까지 서울 여의도 더현대에서 한","link":"https://entertain.naver.com/now/read?oid=003&aid=0010899736","retrieved":1639995864767},{"title":"래퍼 자메즈, 마약·데이트폭력 의혹..소속사 \"사실 확인 중\" (네이버 TV연예 ─ 최신뉴스 ─ 뮤직)","contents":"래퍼 자메즈(32, 김성희)가 마약 투약과 데이트 폭력 의혹에 휩싸였다. 20일 온라인 상에는 자메즈의 여자친구라고 주장하는 A씨가 한 카카오톡 오픈 채팅방에 폭로한 내용이 화제가 됐다. 이 A씨는 \"자메즈의 실체","link":"https://entertain.naver.com/now/read?oid=108&aid=0003014223","retrieved":1639995864769},{"title":"레이지본·크라잉넛…온라인 '인디 페스타 밴드 온' (네이버 TV연예 ─ 최신뉴스 ─ 뮤직)","contents":"[서울=뉴시스]이재훈 기자 = 인디음악 축제 '인디 페스타 밴드 온'이 오는 21~22일 온라인을 통해 관객들을 만난다. 종로문화재단(대표 윤영민)과 한국예술인복지재단(대표 박영정)이 글로벌 숏폼 모바일 비디오 플랫","link":"https://entertain.naver.com/now/read?oid=003&aid=0010899733","retrieved":1639995864770},{"title":"블랙핑크 로제, 근접샷에도 굴욕없는 미모 [스타IN★] (네이버 TV연예 ─ 최신뉴스 ─ 뮤직)","contents":"걸 그룹 블랙핑크의 멤버 로제가 초근접샷을 공개했다. 로제는 지난 19일 오후 자신의 인스타그램에 두 장의 사진을 게재했다. 사진에는 가까운 거리에서 카메라를 보는 로제의 모습이 담겨 있다. 초근접샷임에도 굴욕없는","link":"https://entertain.naver.com/now/read?oid=108&aid=0003014222","retrieved":1640018129338},{"title":"‘유쾌한혜진이 유쾌한콘서트’ 연다 (네이버 TV연예 ─ 최신뉴스 ─ 뮤직)","contents":"[스포츠경향] ‘트롯신이떳다’, ‘미스트롯2’, ‘아침마당’ 등으로 얼굴을 알린 혜진이가 정규1집 ‘눈물잔,맛보고가세요’ 쇼케이스 겸 단독 콘서트를 개최한다. 이번 콘서트는 혜진이의 1집 수록곡을 6인조 EuReKa","link":"https://entertain.naver.com/now/read?oid=144&aid=0000782135","retrieved":1639995864772},{"title":"비투비 이민혁 측 \"코로나19 음성, 백신 접종 완료 못 해 자가격리\" [공식입장] (네이버 TV연예 ─ 최신뉴스 ─ 뮤직)","contents":"(엑스포츠뉴스 김유진 기자) 그룹 비투비 이민혁이 신종 코로나바이러스 감염증(코로나19) 음성 판정을 받았지만 자가격리에 들어간다. 20일 이민혁의 소속사 큐브엔터테인먼트는 \"이민혁이 스케줄 중 코로나19 확진자와","link":"https://entertain.naver.com/now/read?oid=311&aid=0001387704","retrieved":1639995864773},{"title":"몽환적 분위기에 힙 한스푼..에스파의 'Dreams Come True' [6시★살롱] (네이버 TV연예 ─ 최신뉴스 ─ 뮤직)","contents":"그룹 에스파(aespa)가 S.E.S.의 명곡을 재해석했다. 에스파는 20일 오후 6시 '드림스 컴 트루 (Dreams Come True)' 음원과 뮤직비디오를 공개했다. 1998년 발표한 S.E.S. 정규 2집 타","link":"https://entertain.naver.com/now/read?oid=108&aid=0003014212","retrieved":1639992224613},{"title":"대한민국 인디씬 과거 현재 그리고 미래 ‘인디 페스타 밴드 온’ (네이버 TV연예 ─ 최신뉴스 ─ 뮤직)","contents":"[스포츠경향] 인디 씬(Scene)의 과거와 현재 그리고 미래를 모두 만날 수 있는 축제 ‘인디 페스타 밴드 온’이 오는 21일부터 22일까지 온라인을 통해 관객들을 만난다. 종로문화재단(대표 윤영민)과 한국예술인복","link":"https://entertain.naver.com/now/read?oid=144&aid=0000782130","retrieved":1639992224613},{"title":"방탄소년단 뷔, 악성 유튜버 고소한다..\"과자값 나오겠네\" (네이버 TV연예 ─ 최신뉴스 ─ 뮤직)","contents":"보이 그룹 방탄소년단의 뷔가 악성 루머를 퍼트린 유튜버에게 법적 대응을 하겠다고 밝혔다. 20일 방탄소년단 팬 커뮤니티 위버스 게시판에는 한 팬이 뷔에 대한 악성 루머를 퍼뜨리는 유튜버의 영상을 캡처해 올렸다. 이를","link":"https://entertain.naver.com/now/read?oid=108&aid=0003014210","retrieved":1639992224616},{"title":"1415 \"英 'BBC 뮤직어워드' 목표, 영어 연습 더 하면…\" [엑's 인터뷰②] (네이버 TV연예 ─ 최신뉴스 ─ 뮤직)","contents":"(엑스포츠뉴스 이슬 기자) ([엑's 인터뷰①]에 이어) 인디 팝 듀오 1415가 영국 'BBC 뮤직어워드'가 목표라고 밝혔다. 지난 8일 세 번째 EP 'naps!(냅스)'를 발매한 1415는 최근 엑스포츠뉴스와","link":"https://entertain.naver.com/now/read?oid=311&aid=0001387699","retrieved":1639992224616},{"title":"김준수 ‘옷소매’ OST 발매, 이준호 절절한 마음 담은 곡 [앳뉴스] (네이버 TV연예 ─ 최신뉴스 ─ 뮤직)","contents":"[앳스타일 황연도 기자] 가수 김준수(XIA)가 ‘옷소매 붉은 끝동’의 감동을 OST로도 전해준다. 20일 오후 6시 각종 온라인 음원 사이트를 통해 김준수(XIA)가 가창에 참여한 MBC 금토드라마 ‘옷소매 붉은","link":"https://entertain.naver.com/now/read?oid=415&aid=0000006842","retrieved":1639992224617},{"title":"비투비 이민혁, 코로나 음성…\"25일까지 자가격리\" (네이버 TV연예 ─ 최신뉴스 ─ 뮤직)","contents":"[서울=뉴시스]이재훈 기자 = 그룹 '비투비' 멤버 이민혁이 코로나19 음성 판정을 받았으나 당분간 자가격리한다. 소속사 큐브 엔터테인먼트는 20일 \"이민혁이 스케줄 중 코로나19 확진자와 동선이 겹친 사실을 확인해","link":"https://entertain.naver.com/now/read?oid=003&aid=0010899687","retrieved":1639992224618},{"title":"'2000년대생' 에스파가 재현한 '원조 요정 감성' [쥬크박스] (네이버 TV연예 ─ 최신뉴스 ─ 뮤직)","contents":"(엑스포츠뉴스 조혜진 기자) 그룹 에스파(aespa) 버전의 'Dreams Come True(드림스 컴 트루)'가 탄생했다. SM엔터테인먼트(이하 SM)와 유튜브가 함께 진행하는 리마스터링 프로젝트의 일환인 에스파의","link":"https://entertain.naver.com/now/read?oid=311&aid=0001387697","retrieved":1639992224621},{"title":"1415 \"데이식스 원필 피처링…잠 못 자는 경우 많이 봤다\" [엑's 인터뷰①] (네이버 TV연예 ─ 최신뉴스 ─ 뮤직)","contents":"(엑스포츠뉴스 이슬 기자) 인디 팝 듀오 1415가 데이식스 원필이 참여한 신곡 'naps!'를 소개했다. 지난 8일 1415는 세 번째 EP 'naps!(냅스)'를 발매했다. 'naps!'는 지친 일상과 숨 막히는","link":"https://entertain.naver.com/now/read?oid=311&aid=0001387696","retrieved":1639992224621},{"title":"에스파 힙·S.E.S. 몽환·보아 파워가 만나면…'드림스 컴 트루'[신곡읽기] (네이버 TV연예 ─ 최신뉴스 ─ 뮤직)","contents":"[스포티비뉴스=장진리 기자] 그룹 에스파가 '대선배' S.E.S.와 만났다. 에스파는 20일 오후 6시 S.E.S. 히트곡을 리메이크한 '드림스 컴 트루' 음원과 뮤직비디오를 발표했다. '드림스 컴 트루'는 1998","link":"https://entertain.naver.com/now/read?oid=477&aid=0000334239","retrieved":1639992224622},{"title":"[팝's신곡]\"Let's bring back to 90's\"‥에스파, 새로운 'Dreams Come True' (네이버 TV연예 ─ 최신뉴스 ─ 뮤직)","contents":"[헤럴드POP=김나율기자]그룹 에스파가 S.E.S 명곡을 재해석했다. 20일 오후 6시 에스파의 'Dreams Come True'(드림스 컴 트루) 음원과 뮤직비디오가 공개됐다. 에스파는 소속사 SM과 유튜브가 진행","link":"https://entertain.naver.com/now/read?oid=112&aid=0003511816","retrieved":1639992224623},{"title":"가수 로시, 네이버웹툰 ‘아는 여자애’ OST 발매…귀여운 집착송 ‘미리 좀 말해주지 그랬어 (ENFP)’ (네이버 TV연예 ─ 최신뉴스 ─ 뮤직)","contents":"[스포츠경향] 가수 로시, 네이버웹툰 ‘아는 여자애’ OST 발매…귀여운 집착송 ‘미리 좀 말해주지 그랬어 (ENFP)’ 가수 로시가 네이버웹툰 ‘아는 여자애’ OST로 특별한 러브송을 선보인다. 20일 오후 6시","link":"https://entertain.naver.com/now/read?oid=144&aid=0000782121","retrieved":1639992224624},{"title":"김사월, 21일 ‘어사와 조이’ OST 발표 (네이버 TV연예 ─ 최신뉴스 ─ 연예가화제)","contents":"포크 싱어송라이터 김사월이 tvN 월화드라마 ‘어사와 조이’(연출 유종선, 남성우, 정여진 ‧ 극본 이재윤) 세 번째 OST의 가창자로 나선다. 21일 정오 발매되는 세 번째 OST ‘나의 하루 끝에’는","link":"https://entertain.naver.com/now/read?oid=382&aid=0000952104","retrieved":1640027935648},{"title":"서울대 백민주 “‘내캐디’ 출연 계기는 김성주” (네이버 TV연예 ─ 최신뉴스 ─ 연예가화제)","contents":"‘내 이름은 캐디’ SKY 대학생들의 대격돌이 펼쳐진다. 오는 22일(수) IHQ 예능프로그램 ‘내 이름은 캐디’ 7회 방송에서는 ‘캐디’ 이승철, 김성주, 안정환과 ‘SKY’ 대학생들이 대한민국 최고의 ‘골프’ 명","link":"https://entertain.naver.com/now/read?oid=382&aid=0000952103","retrieved":1640027935648},{"title":"‘알타보이즈’ SF9 유태양, 뮤지컬 신고식 성공적 (네이버 TV연예 ─ 최신뉴스 ─ 연예가화제)","contents":"그룹 SF9 유태양이 뮤지컬 배우로 성공적인 신고식을 마쳤다. 유태양은 지난 18일 KBS 아레나에서 개막한 뮤지컬 '알타보이즈'에서 후안 역을 맡았다. '알타보이즈'는 각박한 현실을 사는 힘겨운 영혼들을 음악으로","link":"https://entertain.naver.com/now/read?oid=382&aid=0000952102","retrieved":1640024829883},{"title":"노을 “2년 만에 관객 만나 행복” 서울 공연 성료 (네이버 TV연예 ─ 최신뉴스 ─ 연예가화제)","contents":"그룹 노을이 관객들의 뜨거운 박수 속에 서울 공연을 마쳤다. 노을이 지난 금요일부터 3일간(17-19일) 코엑스 오디토리움에서 열린 2021 전국투어 콘서트 '노을이 내린 밤'으로 서울 관객들과 만났다. 코로나19로","link":"https://entertain.naver.com/now/read?oid=382&aid=0000952101","retrieved":1640024829884},{"title":"유영재, ‘춘정지란’ 출연…첫 주연 (네이버 TV연예 ─ 최신뉴스 ─ 연예가화제)","contents":"가수 겸 배우 유영재가 ‘춘정지란’ 주연으로 출연한다. ‘춘정지란’(연출 이창한/극본 유지연)은 노비 신분을 벗으려는 주인공이 여장 남자로 위장해 혼인하게 되면서 벌어지는 아찔한 세 남자의 청춘 로맨스 사극이다. 웹","link":"https://entertain.naver.com/now/read?oid=382&aid=0000952100","retrieved":1640021378849},{"title":"미래소년 손동표, ‘온에어’ 첫 공연 성공적 (네이버 TV연예 ─ 최신뉴스 ─ 연예가화제)","contents":"그룹 미래소년 손동표가 '온에어(ONAIR)'에서 DJ로 변신해 첫 공연을 성공적으로 올렸다. '온에어'는 팬들이 궁금해하는 질문에 직접 답하고 소통하는 보이는 라디오 형식으로 국내뿐 아니라 해외 팬들까지 한자리에서","link":"https://entertain.naver.com/now/read?oid=382&aid=0000952099","retrieved":1640018136315},{"title":"'2021 자랑스러운 한양 언론인상'에 송대근·조혜련 선정 (네이버 TV연예 ─ 최신뉴스 ─ 연예가화제)","contents":"한양대 언론정보대학원 총동문회는 20일 ‘2021 자랑스러운 한양 언론인상’ 수상자로 송대근 언론중재위 중재위원(전 스포츠동아 대표·사진 왼쪽)과 방송인 조혜련을 선정했다. 송대근 위원은 동아일보에 입사해 사회2부장","link":"https://entertain.naver.com/now/read?oid=022&aid=0003649641","retrieved":1640018136316},{"title":"“우리도 송가인처럼…” 팬클럽 ‘어게인’ 이웃돕기 성금 기부 (네이버 TV연예 ─ 최신뉴스 ─ 연예가화제)","contents":"가수 송가인의 팬카페 ‘AGAIN(어게인)’ 전북 팬들이 20일 전북사회복지공동모금회를 찾아 불우이웃 돕기 성금 115만500원을 기부하며 기념촬영하고 있다. 사랑의열매 제공 신종 코로나바이러스 감염증(코로나19)","link":"https://entertain.naver.com/now/read?oid=022&aid=0003649592","retrieved":1640018136317},{"title":"위아이 김요한, 청량美 무장…‘학교 2021’ 비하인드컷 (네이버 TV연예 ─ 최신뉴스 ─ 연예가화제)","contents":"그룹 위아이(WEi) 김요한이 청량한 분위기로 무장했다. 소속사 위엔터테인먼트는 공식 SNS 및 포스트를 통해 김요한의 KBS2 수목드라마 ‘학교 2021’ 촬영 현장 비하인드 컷을 공개했다. 학교의 안팎을 오가며","link":"https://entertain.naver.com/now/read?oid=382&aid=0000952098","retrieved":1640018136318},{"title":"수현 \"♥재미교포 남편 육아 좋아해..부부싸움 無\"→김윤지, 인생 최고 몸무게 '55kg'에 충격 ('동상이몽2')[종합] (네이버 TV연예 ─ 최신뉴스 ─ 연예가화제)","contents":"[스포츠조선 조윤선 기자] 배우 수현이 재미교포 사업가 남편과의 러브 스토리를 최초로 공개했다. 20일 방송된 SBS '동상이몽2-너는 내 운명'에서는 수현과 재미교포 사업가 남편의 러브 스토리, 김윤지의 다이어트","link":"https://entertain.naver.com/now/read?oid=076&aid=0003814304","retrieved":1640018136318},{"title":"‘한 사람만’ 윤보라, 수녀로 변신…단아하고 내추럴한 매력[M+★SNS] (네이버 TV연예 ─ 최신뉴스 ─ 연예가화제)","contents":"씨스타 출신 윤보라가 수녀로 변신했다. 윤보라는 지난 20일 오후 자신의 인스타그램에 “한 사람만”이라는 글과 사진을 게재했다. 사진 속에는 수녀로 변신한 그의 전신샷이 담겨 있다. 수녀동 표지판을 가리키는 윤보라는","link":"https://entertain.naver.com/now/read?oid=057&aid=0001629710","retrieved":1640018136322},{"title":"포레스텔라, 서울 콘서트 성료+자체 시상식까지 (네이버 TV연예 ─ 최신뉴스 ─ 연예가화제)","contents":"크로스오버 그룹 포레스텔라(Forestella)가 서울 콘서트를 성공적으로 마쳤다. 포레스텔라(강형호, 고우림, 배두훈, 조민규)는 지난 18일과 19일 서울 장충체육관에서 '2021-22 포레스텔라 콘서트 - Th","link":"https://entertain.naver.com/now/read?oid=382&aid=0000952097","retrieved":1640018136323},{"title":"블랙핑크 로제, 절친 혜리 드라마 홍보요정 자처 ‘훈훈’ [똑똑SNS] (네이버 TV연예 ─ 최신뉴스 ─ 연예가화제)","contents":"블랙핑크 로제가 혜리의 새 드라마 ‘꽃 피면 달 생각하고’ 홍보요정을 자처했다. 로제는 20일 오후 자신의 인스타그램 스토리에 “여러분 오늘 밤 9시 30분 혜리 언니 새 드라마 ‘꽃 피면 달 생각하고’ 첫 방송 한","link":"https://entertain.naver.com/now/read?oid=410&aid=0000838971","retrieved":1640013814258},{"title":"배우 유연석 조승우 이도현, 마음까지 훈훈한 유기견 아빠들 [TF확대경] (네이버 TV연예 ─ 최신뉴스 ─ 연예가화제)","contents":"'동물 사랑' 실천에 옮긴 남자 배우들…선한 영향력 전파 유연석 조승우 이도현 등 남자 배우들의 '유기견 아빠' 일상이 선한 영향력과 함께 따뜻함을 전파해 시선을 받고 있다. 유연석은 지난 16일 자신의 유튜브 채널","link":"https://entertain.naver.com/now/read?oid=629&aid=0000122703","retrieved":1640013814260},{"title":"나태주 오늘(21일) 생일…트롯픽 이벤트 주인공 [DA:차트] (네이버 TV연예 ─ 최신뉴스 ─ 연예가화제)","contents":"나태주 오늘(21일) 생일…트롯픽 이벤트 주인공 [DA:차트] 가수 나태주가 트롯픽 생일 이벤트를 받는다. 21일 트롯 문화를 사랑하는 사람들을 응원하는 서비스 트롯픽(trotpick)에 따르면 나태주는 12월 생일","link":"https://entertain.naver.com/now/read?oid=382&aid=0000952096","retrieved":1640013814261},{"title":"'태권트롯맨' 나태주, 생일 맞아 팬들의 특별 선물 (네이버 TV연예 ─ 최신뉴스 ─ 연예가화제)","contents":"\"나태주 생일 축하해\" 트로트가수 나태주가 생일을 맞아 팬들에게 잊지 못할 선물을 받았다. 팬앤스타는 21일 서울 광진구 건대입구 CM보드에서 광고 중인 나태주 생일 축하 이벤트 사진을 공개했다. 나태주의 팬들은 지","link":"https://entertain.naver.com/now/read?oid=629&aid=0000122702","retrieved":1640013814262},{"title":"윤하 ‘별의 조각’, 美빌보드 선정 올해의 베스트 K팝 (네이버 TV연예 ─ 최신뉴스 ─ 연예가화제)","contents":"가수 윤하가 미국 타임지에 이어 빌보드의 극찬을 받았다. 윤하의 정규 6집 'END THEORY(엔드 띠어리)'의 타이틀곡 '별의 조각'은 지난 17일(현지시간) 미국 음악 전문 매체 빌보드(Billboard) 공식","link":"https://entertain.naver.com/now/read?oid=382&aid=0000952095","retrieved":1640013814263},{"title":"김윤지 \"리즈 시절 169cm·48kg→현재 55kg..인생 최고 몸무게\" ('동상이몽2') (네이버 TV연예 ─ 최신뉴스 ─ 연예가화제)","contents":"[스포츠조선 조윤선 기자] 김윤지가 몸무게를 공개했다. 20일 방송된 SBS '동상이몽2-너는 내 운명'에서는 프로필 사진 촬영을 앞두고 몸매 관리에 들어간 김윤지의 모습이 그려졌다. 최근 새로운 소속사와 계약을 맺","link":"https://entertain.naver.com/now/read?oid=076&aid=0003814299","retrieved":1640013814264},{"title":"'한방병원장♥' 장영란, '대기업 임원 며느리' 아옳이와 만남에 \"밝은 기운 얻어\" [TEN★] (네이버 TV연예 ─ 최신뉴스 ─ 연예가화제)","contents":"[텐아시아=김지원 기자] 방송인 장영란이 인플루언서 아옳이와 만남을 기뻐했다. 장영란은 20일 자신의 인스타그램에 \"너무 밝은 기운을 가진 아옳이 민영씨를 만났어요. 어찌나 이쁘고 어찌나 상큼하던지 밝은 기운 많이","link":"https://entertain.naver.com/now/read?oid=312&aid=0000519318","retrieved":1640013814264},{"title":"‘동상이몽2’ 김윤지, ♥최우성 경악 다이어트 비법 [TV체크] (네이버 TV연예 ─ 최신뉴스 ─ 연예가화제)","contents":"20일(월) SBS '동상이몽2 - 너는 내 운명‘(이하 '너는 내 운명')에서는 김윤지의 다이어트 비법이 공개됐다. 최근 새로운 소속사와 계약을 맺은 김윤지가 프로필 사진 촬영을 위해 다이어트에 나섰다. 이에 김윤","link":"https://entertain.naver.com/now/read?oid=382&aid=0000952094","retrieved":1640013814265},{"title":"'프랑스댁' 구재이, ♥교수 남편+붕어빵 아들과 데이트…남부러울 것 없는 하루하루 [TEN★] (네이버 TV연예 ─ 최신뉴스 ─ 연예가화제)","contents":"[텐아시아=김지원 기자] 배우 구재이가 프랑스에서 육아 일상을 전했다. 구재이는 20일 자신의 인스타그램에 \"귀여운 하루하루+356\"라고 글을 올렸다. 구재이는 아들의 일상적 모습을 찍은 사진도 올렸다. 개구쟁이 같","link":"https://entertain.naver.com/now/read?oid=312&aid=0000519317","retrieved":1640010026002},{"title":"”임영웅 단독 콘서트 축하“…팬들, 선한 영향력 동참 ing (네이버 TV연예 ─ 최신뉴스 ─ 연예가화제)","contents":"임영웅의 팬클럽 ‘영웅시대’ 회원들이 오는 26일 오후 9시 15분 KBS 2TV에서 열리는 송년특집 ‘We’re HERO’ 임영웅 단독콘서트 방송을 축하하며 기부와 후원을 이어가고 있다. 임영웅의 팬클럽 ‘웅바라기","link":"https://entertain.naver.com/now/read?oid=410&aid=0000838967","retrieved":1640010026003},{"title":"첫방 ‘한 사람만’ 안은진 “입체적 캐릭터들, 다 사랑스러워” [DA:투데이] (네이버 TV연예 ─ 최신뉴스 ─ 연예가화제)","contents":"JTBC 새 월화드라마 ‘한 사람만’(극본 문정민 연출 오현종)이 오늘(20일) 첫 방송됐다. 2021년의 끝, 안은진-김경남-강예원-박수영의 기적 같은 여정을 통해 따뜻함을 선물할 ‘한 사람만’은 호스피스에서 만난","link":"https://entertain.naver.com/now/read?oid=382&aid=0000952093","retrieved":1640010026004},{"title":"온앤오프, 'Goosebumps' 활동 성료…커리어 하이→전원입대 (네이버 TV연예 ─ 최신뉴스 ─ 연예가화제)","contents":"‘명곡 맛집’ 온앤오프(ONF)가 입대를 앞두고 또 한 번 자체 기록을 경신하며 새 앨범 공식 활동을 종료했다. 지난 3일 여섯 번째 미니앨범 ‘Goosebumps’를 발매하며 컴백한 온앤오프는 지난 19일 참석한","link":"https://entertain.naver.com/now/read?oid=009&aid=0004896577","retrieved":1640010026004},{"title":"'싱글맘' 이지현, \"비행기서 떠들어서 죄송합니다\" 두 자녀와 떠난 제주도 여행 [TEN★] (네이버 TV연예 ─ 최신뉴스 ─ 연예가화제)","contents":"[텐아시아=김지원 기자] 그룹 쥬얼리 출신 방송인 이지현이 아이들과 제주도 여행을 떠났다. 이지현은 20일 자신의 인스타그램에 \"제주 놀러왔어요. 지금 우리 셋 너무 행복합니다. 비행기에서 롤러코스터~ 착륙~ 마치","link":"https://entertain.naver.com/now/read?oid=312&aid=0000519316","retrieved":1640010026005},{"title":"\"정해인 응원했는데\"…푸라닭도 '설강화' 광고 손절 (네이버 TV연예 ─ 최신뉴스 ─ 해외연예)","contents":"[서울=뉴시스] 최지윤 기자 = 치킨 브랜드 푸라닭이 JTBC 주말극 '설강화' 광고를 중단한다. 푸라닭은 설강화 3대 제작지원사 중 한 곳으로, 설강화 주연인 탤런트 정해인이 모델로 활동 중이다. 푸라닭은 20일","link":"https://entertain.naver.com/now/read?oid=003&aid=0010899710","retrieved":1639992237935},{"title":"덴젤 워싱턴, 배우 은퇴 시사…\"맡을 수 있는 역할 많지 않아\" [엑's 할리우드] (네이버 TV연예 ─ 최신뉴스 ─ 해외연예)","contents":"(엑스포츠뉴스 이창규 기자) 할리우드 배우 덴젤 워싱턴이 은퇴를 시사했다. 덴젤 워싱턴은 지난 16일(현지시간) 엔터테인먼트 투데이(ET)와의 인터뷰에서 \"이번 작품('맥베스의 비극')의 캐릭터처럼 나도 연기 경력의","link":"https://entertain.naver.com/now/read?oid=311&aid=0001387673","retrieved":1639988956888},{"title":"샘김, 태국 아티스트 뮤 수파싯과 컬래버…'비포 4:30' (네이버 TV연예 ─ 최신뉴스 ─ 해외연예)","contents":"[서울=뉴시스]김예지 인턴 기자 = 가수 샘김이 태국 대표 아티스트 뮤 수파싯(Mew Suppasit)과 손잡고 글로벌 컬래버 신곡을 발매했다. 20일 소속사 안테나에 따르면 샘김은 이날 0시 뮤 수파싯과의 글로벌","link":"https://entertain.naver.com/now/read?oid=003&aid=0010899471","retrieved":1639988941401},{"title":"몬스타엑스, 美 '징글볼 투어' 성료…\"전세계 몬베베들께 감사\" (네이버 TV연예 ─ 최신뉴스 ─ 해외연예)","contents":"[서울=뉴시스]김예지 인턴 기자 = 그룹 몬스타엑스(MONSTA X)가 미국 '징글볼(Jingle Ball)' 투어를 성료했다. 20일 스타쉽엔터테인먼트에 따르면 몬스타엑스는 지난 16일(이하 미국 현지 시간) 애틀","link":"https://entertain.naver.com/now/read?oid=003&aid=0010899305","retrieved":1639984952276},{"title":"‘섹스 앤 더 시티’ 크리스 노스, 여성 2인 성폭행 혐의…소속사도 손절[할리우드비하인드] (네이버 TV연예 ─ 최신뉴스 ─ 해외연예)","contents":"[뉴스엔 이민지 기자] 배우 크리스 노스가 성폭행 혐의로 논란에 휩싸였다. 베니티 페어는 12월 18일(현지시간) 배우 크리스 노스 에이전시가 크리스 노스를 손절했다고 보도했다. 크리스 노스는 두 명의 여성을 성폭행","link":"https://entertain.naver.com/now/read?oid=609&aid=0000524540","retrieved":1639984966161},{"title":"안은진-강예원-박수영 '미녀 삼총사' [MK포토] (네이버 TV연예 ─ 최신뉴스 ─ 해외연예)","contents":"20일 오후 JTBC 새 월화드라마 ‘한 사람만’ 온라인 제작발표회가 열렸다. 이날 제작발표회에는 오현종 감독, 안은진, 김경남, 강예원, 박수영이 참석했다. 안은진, 강예원, 박수영이 제작발표회에 앞서 포토타임을","link":"https://entertain.naver.com/now/read?oid=410&aid=0000838916","retrieved":1639981661287},{"title":"김경남 '세 미녀들과 함께' [MK포토] (네이버 TV연예 ─ 최신뉴스 ─ 해외연예)","contents":"20일 오후 JTBC 새 월화드라마 ‘한 사람만’ 온라인 제작발표회가 열렸다. 이날 제작발표회에는 오현종 감독, 안은진, 김경남, 강예원, 박수영이 참석했다. 김경남과 안은진 등 출연진들이 제작발표회에 앞서 포토타임","link":"https://entertain.naver.com/now/read?oid=410&aid=0000838915","retrieved":1639981661287},{"title":"김경남 '무대 위의 청일점 [MK포토] (네이버 TV연예 ─ 최신뉴스 ─ 해외연예)","contents":"20일 오후 JTBC 새 월화드라마 ‘한 사람만’ 온라인 제작발표회가 열렸다. 이날 제작발표회에는 오현종 감독, 안은진, 김경남, 강예원, 박수영이 참석했다. 김경남과 안은진 등 출연진들이 제작발표회에 앞서 포토타임","link":"https://entertain.naver.com/now/read?oid=410&aid=0000838914","retrieved":1639981661291},{"title":"몬스타엑스 민혁 \"새해, 몬베베와의 추억들로 가득하길\" (네이버 TV연예 ─ 최신뉴스 ─ 해외연예)","contents":"[서울=뉴시스]김예지 인턴 기자 = 몬스타엑스 민혁이 새해 다짐과 함께 팬사랑을 드러냈다. 20일 라이프스타일 매거진 '싱글즈'에 따르면 민혁은 최근 '싱글즈' 1월호 화보를 촬영하면서 아티스트로서의 소신과 올해에","link":"https://entertain.naver.com/now/read?oid=003&aid=0010898858","retrieved":1639981661292},{"title":"안은진 '살짝 시스루 패션' [MK포토] (네이버 TV연예 ─ 최신뉴스 ─ 해외연예)","contents":"20일 오후 JTBC 새 월화드라마 ‘한 사람만’ 온라인 제작발표회가 열렸다. 이날 제작발표회에는 오현종 감독, 안은진, 김경남, 강예원, 박수영이 참석했다. 안은진이 제작발표회에 앞서 포토타임을 갖고 있다. 사진=","link":"https://entertain.naver.com/now/read?oid=410&aid=0000838911","retrieved":1639981661293},{"title":"김경남-안은진, '한 사람만' 기대하세요 [MK포토] (네이버 TV연예 ─ 최신뉴스 ─ 해외연예)","contents":"20일 오후 JTBC 새 월화드라마 ‘한 사람만’ 온라인 제작발표회가 열렸다. 이날 제작발표회에는 오현종 감독, 안은진, 김경남, 강예원, 박수영이 참석했다. 김경남과 안은진이 제작발표회에 앞서 포토타임을 갖고 있다","link":"https://entertain.naver.com/now/read?oid=410&aid=0000838910","retrieved":1639981661294},{"title":"김경남-안은진 '한 사람만' 커플 [MK포토] (네이버 TV연예 ─ 최신뉴스 ─ 해외연예)","contents":"20일 오후 JTBC 새 월화드라마 ‘한 사람만’ 온라인 제작발표회가 열렸다. 이날 제작발표회에는 오현종 감독, 안은진, 김경남, 강예원, 박수영이 참석했다. 김경남과 안은진이 제작발표회에 앞서 포토타임을 갖고 있다","link":"https://entertain.naver.com/now/read?oid=410&aid=0000838909","retrieved":1639981661294},{"title":"유승호-혜리, 잘 어울리는 '꽃달' 커플 [MK포토] (네이버 TV연예 ─ 최신뉴스 ─ 해외연예)","contents":"20일 오후 KBS 새 드라마 ‘꽃 피면 달 생각하고’ 온라인 제작발표회가 열렸다. 이날 제작발표회에는 황인혁 감독, 유승호, 이혜리, 변우석, 강미나가 참석했다. 유승호와 이혜리가 제작발표회에 앞서 포토타임을 갖고","link":"https://entertain.naver.com/now/read?oid=410&aid=0000838906","retrieved":1639977736195},{"title":"유승호-혜리 '바라만 봐도 좋아' [MK포토] (네이버 TV연예 ─ 최신뉴스 ─ 해외연예)","contents":"20일 오후 KBS 새 드라마 ‘꽃 피면 달 생각하고’ 온라인 제작발표회가 열렸다. 이날 제작발표회에는 황인혁 감독, 유승호, 이혜리, 변우석, 강미나가 참석했다. 유승호와 이혜리가 제작발표회에 앞서 포토타임을 갖고","link":"https://entertain.naver.com/now/read?oid=410&aid=0000838905","retrieved":1639977736197},{"title":"혜리 '무표정도 예뻐' [MK포토] (네이버 TV연예 ─ 최신뉴스 ─ 해외연예)","contents":"20일 오후 KBS 새 드라마 ‘꽃 피면 달 생각하고’ 온라인 제작발표회가 열렸다. 이날 제작발표회에는 황인혁 감독, 유승호, 이혜리, 변우석, 강미나가 참석했다. 이혜리가 제작발표회에 앞서 포토타임을 갖고 있다.","link":"https://entertain.naver.com/now/read?oid=410&aid=0000838904","retrieved":1639977736199},{"title":"혜리 '달 생각하는 중' [MK포토] (네이버 TV연예 ─ 최신뉴스 ─ 해외연예)","contents":"20일 오후 KBS 새 드라마 ‘꽃 피면 달 생각하고’ 온라인 제작발표회가 열렸다. 이날 제작발표회에는 황인혁 감독, 유승호, 이혜리, 변우석, 강미나가 참석했다. 이혜리가 제작발표회에 앞서 포토타임을 갖고 있다.","link":"https://entertain.naver.com/now/read?oid=410&aid=0000838903","retrieved":1639977736199},{"title":"혜리 '상큼 손인사' [MK포토] (네이버 TV연예 ─ 최신뉴스 ─ 해외연예)","contents":"20일 오후 KBS 새 드라마 ‘꽃 피면 달 생각하고’ 온라인 제작발표회가 열렸다. 이날 제작발표회에는 황인혁 감독, 유승호, 이혜리, 변우석, 강미나가 참석했다. 이혜리가 제작발표회에 앞서 포토타임을 갖고 있다.","link":"https://entertain.naver.com/now/read?oid=410&aid=0000838902","retrieved":1639977736200},{"title":"혜리 '두 손 모아 하트' [MK포토] (네이버 TV연예 ─ 최신뉴스 ─ 해외연예)","contents":"20일 오후 KBS 새 드라마 ‘꽃 피면 달 생각하고’ 온라인 제작발표회가 열렸다. 이날 제작발표회에는 황인혁 감독, 유승호, 이혜리, 변우석, 강미나가 참석했다. 이혜리가 제작발표회에 앞서 포토타임을 갖고 있다.","link":"https://entertain.naver.com/now/read?oid=410&aid=0000838901","retrieved":1639977736201},{"title":"NCT, 정규3집 한터→알라딘 음반차트 주간1위 (네이버 TV연예 ─ 최신뉴스 ─ 해외연예)","contents":"[서울=뉴시스]김예지 인턴 기자 = 엔시티(NCT)가 정규 3집 '유니버스(Universe)'로 주간 음반 차트 1위를 석권했다. 20일 SM엔터테인먼트에 따르면, 지난 14일 발매된 엔시티 정규 3집 '유니버스'는","link":"https://entertain.naver.com/now/read?oid=003&aid=0010898699","retrieved":1639977721276},{"title":"'섹스 앤 더 시티' 男배우, 여성 3명 성폭행 의혹…\"아내 화났다\" (네이버 TV연예 ─ 최신뉴스 ─ 해외연예)","contents":"[배우 크리스 노스, 결국 소속사 퇴출] 미국의 인기드라마 '섹스 앤드 더 시티'에서 주인공 캐리의 남자친구 '빅' 역으로 유명한 크리스 노스(67)가 2004년부터 세 명의 여성을 성폭행한 혐의로 고소당한 가운데","link":"https://entertain.naver.com/now/read?oid=008&aid=0004685603","retrieved":1639968087423},{"title":"'스파이더맨' 美 개봉 첫 주 3000억…역대 3위 기록 (네이버 TV연예 ─ 최신뉴스 ─ 해외연예)","contents":"기사내용 요약 '엔드게임' '인피니티 워' 이어 3위 [서울=뉴시스] 손정빈 기자 = 마블의 새 슈퍼히어로 영화 '스파이더맨:노 웨이 홈'(감독 존 왓츠)이 미국 현지에서도 폭발적인 흥행세를 이어가고 있다. 영화는","link":"https://entertain.naver.com/now/read?oid=003&aid=0010897835","retrieved":1639962658918},{"title":"머슬퀸들의 비키니 패션 [MK화보] (네이버 TV연예 ─ 최신뉴스 ─ 해외연예)","contents":"머슬퀸들이 19일 오후 서울 강남구 대치동 세텍에서 열린 '제16회 아시아모델어워즈' 레드카펫 행사에 참석하고 있다.","link":"https://entertain.naver.com/now/read?oid=410&aid=0000838821","retrieved":1639956083641},{"title":"손나은 '감탄 나오는 치명적 미모' [MK화보] (네이버 TV연예 ─ 최신뉴스 ─ 해외연예)","contents":"가수 손나은이 19일 오후 서울 강남구 대치동 세텍에서 열린 '제16회 아시아모델어워즈' 레드카펫 행사에 참석하고 있다.","link":"https://entertain.naver.com/now/read?oid=410&aid=0000838818","retrieved":1639952525478},{"title":"김우석 '멋진 하트' [MK포토] (네이버 TV연예 ─ 최신뉴스 ─ 해외연예)","contents":"가수 김우석이 19일 오후 서울 강남구 대치동 세텍에서 열린 '제16회 아시아모델어워즈' 레드카펫 행사에 참석하고 있다.","link":"https://entertain.naver.com/now/read?oid=410&aid=0000838799","retrieved":1639912673074},{"title":"인사하는 라붐 솔빈 [MK포토] (네이버 TV연예 ─ 최신뉴스 ─ 해외연예)","contents":"라붐 솔빈이 19일 오후 서울 강남구 대치동 세텍에서 열린 '제16회 아시아모델어워즈' 레드카펫 행사에 참석하고 있다.","link":"https://entertain.naver.com/now/read?oid=410&aid=0000838798","retrieved":1639912673076}]}